[{"front": 3.128, "back": 1.061, "right": 2.558, "left": 0.781, "up": 1.609, "down": 1.065, "x": 0.0, "y": 0.0, "z": 1.065, "yaw": 0.0}, {"front": 3.128, "back": 1.061, "right": 2.558, "left": 0.773, "up": 1.605, "down": 1.065, "x": 0.0, "y": 0.0, "z": 1.065, "yaw": 0.0}, {"front": 3.128, "back": 1.061, "right": 2.554, "left": 0.773, "up": 1.605, "down": 1.065, "x": 0.0, "y": 0.0, "z": 1.065, "yaw": 0.0}, {"front": 3.128, "back": 1.061, "right": 2.554, "left": 0.773, "up": 1.605, "down": 1.068, "x": 0.0, "y": 0.0, "z": 1.068, "yaw": 0.0}, {"front": 3.128, "back": 1.061, "right": 2.554, "left": 0.773, "up": 1.605, "down": 1.068, "x": 0.0, "y": 0.0, "z": 1.068, "yaw": 0.0}, {"front": 3.128, "back": 1.061, "right": 2.554, "left": 0.773, "up": 1.605, "down": 1.068, "x": 0.0, "y": 0.0, "z": 1.068, "yaw": 0.0}, {"front": 3.128, "back": 1.061, "right": 2.554, "left": 0.773, "up": 1.605, "down": 1.068, "x": 0.0, "y": 0.0, "z": 1.068, "yaw": 0.0}, {"front": 3.128, "back": 1.061, "right": 2.554, "left": 0.773, "up": 1.605, "down": 1.069, "x": 0.0, "y": 0.0, "z": 1.069, "yaw": 0.0}, {"front": 3.128, "back": 1.061, "right": 2.554, "left": 0.773, "up": 1.605, "down": 1.069, "x": 0.0, "y": 0.0, "z": 1.069, "yaw": 0.0}, {"front": 3.13, "back": 1.061, "right": 2.554, "left": 0.773, "up": 1.605, "down": 1.069, "x": 0.0, "y": 0.0, "z": 1.069, "yaw": 0.0}, {"front": 3.13, "back": 1.065, "right": 2.554, "left": 0.773, "up": 1.605, "down": 1.069, "x": 0.0, "y": 0.0, "z": 1.069, "yaw": 0.0}, {"front": 3.13, "back": 1.065, "right": 2.554, "left": 0.747, "up": 1.602, "down": 1.069, "x": 0.0, "y": 0.0, "z": 1.069, "yaw": 0.0}, {"front": 3.13, "back": 1.065, "right": 2.551, "left": 0.747, "up": 1.602, "down": 1.069, "x": 0.0, "y": 0.0, "z": 1.069, "yaw": 0.0}, {"front": 3.13, "back": 1.065, "right": 2.551, "left": 0.747, "up": 1.602, "down": 1.07, "x": 0.0, "y": 0.0, "z": 1.07, "yaw": 0.0}, {"front": 3.13, "back": 1.065, "right": 2.551, "left": 0.747, "up": 1.602, "down": 1.07, "x": 0.0, "y": 0.0, "z": 1.07, "yaw": 0.0}, {"front": 3.13, "back": 1.065, "right": 2.551, "left": 0.747, "up": 1.602, "down": 1.07, "x": 0.0, "y": 0.0, "z": 1.07, "yaw": 0.0}, {"front": 3.13, "back": 1.065, "right": 2.551, "left": 0.747, "up": 1.602, "down": 1.07, "x": 0.0, "y": 0.0, "z": 1.07, "yaw": 0.0}, {"front": 3.13, "back": 1.065, "right": 2.551, "left": 0.747, "up": 1.602, "down": 1.074, "x": 0.0, "y": 0.0, "z": 1.074, "yaw": 0.0}, {"front": 3.13, "back": 1.065, "right": 2.551, "left": 0.747, "up": 1.602, "down": 1.074, "x": 0.0, "y": 0.0, "z": 1.074, "yaw": 0.0}, {"front": 32.766, "back": 1.065, "right": 2.551, "left": 0.747, "up": 1.602, "down": 1.074, "x": 0.0, "y": 0.0, "z": 1.074, "yaw": 0.0}, {"front": 32.766, "back": 1.068, "right": 2.551, "left": 0.747, "up": 1.602, "down": 1.074, "x": 0.0, "y": 0.0, "z": 1.074, "yaw": 0.0}, {"front": 32.766, "back": 1.068, "right": 2.551, "left": 0.774, "up": 1.605, "down": 1.074, "x": 0.0, "y": 0.0, "z": 1.074, "yaw": 0.0}, {"front": 32.766, "back": 1.068, "right": 2.547, "left": 0.774, "up": 1.605, "down": 1.074, "x": 0.0, "y": 0.0, "z": 1.074, "yaw": 0.0}, {"front": 32.766, "back": 1.068, "right": 2.547, "left": 0.774, "up": 1.605, "down": 1.072, "x": 0.0, "y": 0.0, "z": 1.072, "yaw": 0.0}, {"front": 32.766, "back": 1.068, "right": 2.547, "left": 0.774, "up": 1.605, "down": 1.072, "x": 0.0, "y": 0.0, "z": 1.072, "yaw": 0.0}, {"front": 32.766, "back": 1.068, "right": 2.547, "left": 0.774, "up": 1.605, "down": 1.072, "x": 0.0, "y": 0.0, "z": 1.072, "yaw": 0.0}, {"front": 32.766, "back": 1.068, "right": 2.547, "left": 0.774, "up": 1.605, "down": 1.072, "x": 0.0, "y": 0.0, "z": 1.072, "yaw": 0.0}, {"front": 32.766, "back": 1.068, "right": 2.547, "left": 0.774, "up": 1.605, "down": 1.074, "x": 0.0, "y": 0.0, "z": 1.074, "yaw": 0.0}, {"front": 32.766, "back": 1.068, "right": 2.547, "left": 0.774, "up": 1.605, "down": 1.074, "x": 0.0, "y": 0.0, "z": 1.074, "yaw": 0.0}, {"front": 3.113, "back": 1.068, "right": 2.547, "left": 0.774, "up": 1.605, "down": 1.074, "x": 0.0, "y": 0.0, "z": 1.074, "yaw": 0.0}, {"front": 3.113, "back": 1.072, "right": 2.547, "left": 0.774, "up": 1.605, "down": 1.074, "x": 0.0, "y": 0.0, "z": 1.074, "yaw": 0.0}, {"front": 3.113, "back": 1.072, "right": 2.547, "left": 0.784, "up": 1.6, "down": 1.074, "x": 0.0, "y": 0.0, "z": 1.074, "yaw": 0.0}, {"front": 3.113, "back": 1.072, "right": 2.538, "left": 0.784, "up": 1.6, "down": 1.074, "x": 0.0, "y": 0.0, "z": 1.074, "yaw": 0.0}, {"front": 3.113, "back": 1.072, "right": 2.538, "left": 0.784, "up": 1.6, "down": 1.078, "x": 0.0, "y": 0.0, "z": 1.078, "yaw": 0.0}, {"front": 3.113, "back": 1.072, "right": 2.538, "left": 0.784, "up": 1.6, "down": 1.078, "x": 0.0, "y": 0.0, "z": 1.078, "yaw": 0.0}, {"front": 3.113, "back": 1.072, "right": 2.538, "left": 0.784, "up": 1.6, "down": 1.078, "x": 0.0, "y": 0.0, "z": 1.078, "yaw": 0.0}, {"front": 3.113, "back": 1.072, "right": 2.538, "left": 0.784, "up": 1.6, "down": 1.078, "x": 0.0, "y": 0.0, "z": 1.078, "yaw": 0.0}, {"front": 3.113, "back": 1.072, "right": 2.538, "left": 0.784, "up": 1.6, "down": 1.08, "x": 0.0, "y": 0.0, "z": 1.08, "yaw": 0.0}, {"front": 3.113, "back": 1.072, "right": 2.538, "left": 0.784, "up": 1.6, "down": 1.08, "x": 0.0, "y": 0.0, "z": 1.08, "yaw": 0.0}, {"front": 32.766, "back": 1.072, "right": 2.538, "left": 0.784, "up": 1.6, "down": 1.08, "x": 0.0, "y": 0.0, "z": 1.08, "yaw": 0.0}, {"front": 32.766, "back": 1.059, "right": 2.538, "left": 0.784, "up": 1.6, "down": 1.08, "x": 0.0, "y": 0.0, "z": 1.08, "yaw": 0.0}, {"front": 32.766, "back": 1.059, "right": 2.538, "left": 0.768, "up": 1.595, "down": 1.08, "x": 0.0, "y": 0.0, "z": 1.08, "yaw": 0.0}, {"front": 32.766, "back": 1.059, "right": 2.533, "left": 0.768, "up": 1.595, "down": 1.08, "x": 0.0, "y": 0.0, "z": 1.08, "yaw": 0.0}, {"front": 32.766, "back": 1.059, "right": 2.533, "left": 0.768, "up": 1.595, "down": 1.084, "x": 0.0, "y": 0.0, "z": 1.084, "yaw": 0.0}, {"front": 32.766, "back": 1.059, "right": 2.533, "left": 0.768, "up": 1.595, "down": 1.084, "x": 0.0, "y": 0.0, "z": 1.084, "yaw": 0.0}, {"front": 32.766, "back": 1.059, "right": 2.533, "left": 0.768, "up": 1.595, "down": 1.084, "x": 0.0, "y": 0.0, "z": 1.084, "yaw": 0.0}, {"front": 32.766, "back": 1.059, "right": 2.533, "left": 0.768, "up": 1.595, "down": 1.084, "x": 0.0, "y": 0.0, "z": 1.084, "yaw": 0.0}, {"front": 32.766, "back": 1.059, "right": 2.533, "left": 0.768, "up": 1.595, "down": 1.082, "x": 0.0, "y": 0.0, "z": 1.082, "yaw": 0.0}, {"front": 32.766, "back": 1.059, "right": 2.533, "left": 0.768, "up": 1.595, "down": 1.082, "x": 0.0, "y": 0.0, "z": 1.082, "yaw": 0.0}, {"front": 32.766, "back": 1.059, "right": 2.533, "left": 0.768, "up": 1.595, "down": 1.082, "x": 0.0, "y": 0.0, "z": 1.082, "yaw": 0.0}, {"front": 32.766, "back": 1.071, "right": 2.533, "left": 0.768, "up": 1.595, "down": 1.082, "x": 0.0, "y": 0.0, "z": 1.082, "yaw": 0.0}, {"front": 32.766, "back": 1.071, "right": 2.533, "left": 0.832, "up": 1.589, "down": 1.082, "x": 0.0, "y": 0.0, "z": 1.082, "yaw": 0.0}, {"front": 32.766, "back": 1.071, "right": 2.523, "left": 0.832, "up": 1.589, "down": 1.082, "x": 0.0, "y": 0.0, "z": 1.082, "yaw": 0.0}, {"front": 32.766, "back": 1.071, "right": 2.523, "left": 0.832, "up": 1.589, "down": 1.083, "x": 0.0, "y": 0.0, "z": 1.083, "yaw": 0.0}, {"front": 32.766, "back": 1.071, "right": 2.523, "left": 0.832, "up": 1.589, "down": 1.083, "x": 0.0, "y": 0.0, "z": 1.083, "yaw": 0.0}, {"front": 32.766, "back": 1.071, "right": 2.523, "left": 0.832, "up": 1.589, "down": 1.083, "x": 0.0, "y": 0.0, "z": 1.083, "yaw": 0.0}, {"front": 32.766, "back": 1.071, "right": 2.523, "left": 0.832, "up": 1.589, "down": 1.083, "x": 0.0, "y": 0.0, "z": 1.083, "yaw": 0.0}, {"front": 32.766, "back": 1.071, "right": 2.523, "left": 0.832, "up": 1.589, "down": 1.08, "x": 0.0, "y": 0.0, "z": 1.08, "yaw": 0.0}, {"front": 32.766, "back": 1.071, "right": 2.523, "left": 0.832, "up": 1.589, "down": 1.08, "x": 0.0, "y": 0.0, "z": 1.08, "yaw": 0.0}, {"front": 3.091, "back": 1.071, "right": 2.523, "left": 0.832, "up": 1.589, "down": 1.08, "x": 0.0, "y": 0.0, "z": 1.08, "yaw": 0.0}, {"front": 3.091, "back": 1.074, "right": 2.523, "left": 0.832, "up": 1.589, "down": 1.08, "x": 0.0, "y": 0.0, "z": 1.08, "yaw": 0.0}, {"front": 3.091, "back": 1.074, "right": 2.523, "left": 0.847, "up": 1.581, "down": 1.08, "x": 0.0, "y": 0.0, "z": 1.08, "yaw": 0.0}, {"front": 3.091, "back": 1.074, "right": 2.507, "left": 0.847, "up": 1.581, "down": 1.08, "x": 0.0, "y": 0.0, "z": 1.08, "yaw": 0.0}, {"front": 3.091, "back": 1.074, "right": 2.507, "left": 0.847, "up": 1.581, "down": 1.087, "x": 0.0, "y": 0.0, "z": 1.087, "yaw": 0.0}, {"front": 3.091, "back": 1.074, "right": 2.507, "left": 0.847, "up": 1.581, "down": 1.087, "x": 0.0, "y": 0.0, "z": 1.087, "yaw": 0.0}, {"front": 3.091, "back": 1.074, "right": 2.507, "left": 0.847, "up": 1.581, "down": 1.087, "x": 0.0, "y": 0.0, "z": 1.087, "yaw": 0.0}, {"front": 3.091, "back": 1.074, "right": 2.507, "left": 0.847, "up": 1.581, "down": 1.087, "x": 0.0, "y": 0.0, "z": 1.087, "yaw": 0.0}, {"front": 3.091, "back": 1.074, "right": 2.507, "left": 0.847, "up": 1.581, "down": 1.087, "x": 0.0, "y": 0.0, "z": 1.087, "yaw": 0.0}, {"front": 3.091, "back": 1.074, "right": 2.507, "left": 0.847, "up": 1.581, "down": 1.087, "x": 0.0, "y": 0.0, "z": 1.087, "yaw": 0.0}, {"front": 3.082, "back": 1.074, "right": 2.507, "left": 0.847, "up": 1.581, "down": 1.087, "x": 0.0, "y": 0.0, "z": 1.087, "yaw": 0.0}, {"front": 3.082, "back": 1.087, "right": 2.507, "left": 0.847, "up": 1.581, "down": 1.087, "x": 0.0, "y": 0.0, "z": 1.087, "yaw": 0.0}, {"front": 3.082, "back": 1.087, "right": 2.507, "left": 32.766, "up": 1.592, "down": 1.087, "x": 0.0, "y": 0.0, "z": 1.087, "yaw": 0.0}, {"front": 3.082, "back": 1.087, "right": 2.501, "left": 32.766, "up": 1.592, "down": 1.087, "x": 0.0, "y": 0.0, "z": 1.087, "yaw": 0.0}, {"front": 3.082, "back": 1.087, "right": 2.501, "left": 32.766, "up": 1.592, "down": 1.084, "x": 0.0, "y": 0.0, "z": 1.084, "yaw": 0.0}, {"front": 3.082, "back": 1.087, "right": 2.501, "left": 32.766, "up": 1.592, "down": 1.084, "x": 0.0, "y": 0.0, "z": 1.084, "yaw": 0.0}, {"front": 3.082, "back": 1.087, "right": 2.501, "left": 32.766, "up": 1.592, "down": 1.084, "x": 0.0, "y": 0.0, "z": 1.084, "yaw": 0.0}, {"front": 3.082, "back": 1.087, "right": 2.501, "left": 32.766, "up": 1.592, "down": 1.084, "x": 0.0, "y": 0.0, "z": 1.084, "yaw": 0.0}, {"front": 3.082, "back": 1.087, "right": 2.501, "left": 32.766, "up": 1.592, "down": 1.092, "x": 0.0, "y": 0.0, "z": 1.092, "yaw": 0.0}, {"front": 3.082, "back": 1.087, "right": 2.501, "left": 32.766, "up": 1.592, "down": 1.092, "x": 0.0, "y": 0.0, "z": 1.092, "yaw": 0.0}, {"front": 32.766, "back": 1.087, "right": 2.501, "left": 32.766, "up": 1.592, "down": 1.092, "x": 0.0, "y": 0.0, "z": 1.092, "yaw": 0.0}, {"front": 32.766, "back": 1.09, "right": 2.501, "left": 32.766, "up": 1.592, "down": 1.092, "x": 0.0, "y": 0.0, "z": 1.092, "yaw": 0.0}, {"front": 32.766, "back": 1.09, "right": 2.501, "left": 0.89, "up": 1.589, "down": 1.092, "x": 0.0, "y": 0.0, "z": 1.092, "yaw": 0.0}, {"front": 32.766, "back": 1.09, "right": 2.495, "left": 0.89, "up": 1.589, "down": 1.092, "x": 0.0, "y": 0.0, "z": 1.092, "yaw": 0.0}, {"front": 32.766, "back": 1.09, "right": 2.495, "left": 0.89, "up": 1.589, "down": 1.091, "x": 0.0, "y": 0.0, "z": 1.091, "yaw": 0.0}, {"front": 32.766, "back": 1.09, "right": 2.495, "left": 0.89, "up": 1.589, "down": 1.091, "x": 0.0, "y": 0.0, "z": 1.091, "yaw": 0.0}, {"front": 32.766, "back": 1.09, "right": 2.495, "left": 0.89, "up": 1.589, "down": 1.091, "x": 0.0, "y": 0.0, "z": 1.091, "yaw": 0.0}, {"front": 32.766, "back": 1.09, "right": 2.495, "left": 0.89, "up": 1.589, "down": 1.091, "x": 0.0, "y": 0.0, "z": 1.091, "yaw": 0.0}, {"front": 32.766, "back": 1.09, "right": 2.495, "left": 0.89, "up": 1.589, "down": 1.093, "x": 0.0, "y": 0.0, "z": 1.093, "yaw": 0.0}, {"front": 32.766, "back": 1.09, "right": 2.495, "left": 0.89, "up": 1.589, "down": 1.093, "x": 0.0, "y": 0.0, "z": 1.093, "yaw": 0.0}, {"front": 32.766, "back": 1.09, "right": 2.495, "left": 0.89, "up": 1.589, "down": 1.093, "x": 0.0, "y": 0.0, "z": 1.093, "yaw": 0.0}, {"front": 32.766, "back": 1.092, "right": 2.495, "left": 0.89, "up": 1.589, "down": 1.093, "x": 0.0, "y": 0.0, "z": 1.093, "yaw": 0.0}, {"front": 32.766, "back": 1.092, "right": 2.495, "left": 0.882, "up": 1.586, "down": 1.093, "x": 0.0, "y": 0.0, "z": 1.093, "yaw": 0.0}, {"front": 32.766, "back": 1.092, "right": 2.503, "left": 0.882, "up": 1.586, "down": 1.093, "x": 0.0, "y": 0.0, "z": 1.093, "yaw": 0.0}, {"front": 32.766, "back": 1.092, "right": 2.503, "left": 0.882, "up": 1.586, "down": 1.09, "x": 0.0, "y": 0.0, "z": 1.09, "yaw": 0.0}, {"front": 32.766, "back": 1.092, "right": 2.503, "left": 0.882, "up": 1.586, "down": 1.09, "x": 0.0, "y": 0.0, "z": 1.09, "yaw": 0.0}, {"front": 32.766, "back": 1.092, "right": 2.503, "left": 0.882, "up": 1.586, "down": 1.09, "x": 0.0, "y": 0.0, "z": 1.09, "yaw": 0.0}, {"front": 32.766, "back": 1.092, "right": 2.503, "left": 0.882, "up": 1.586, "down": 1.09, "x": 0.0, "y": 0.0, "z": 1.09, "yaw": 0.0}, {"front": 32.766, "back": 1.092, "right": 2.503, "left": 0.882, "up": 1.586, "down": 1.09, "x": 0.0, "y": 0.0, "z": 1.09, "yaw": 0.0}, {"front": 32.766, "back": 1.092, "right": 2.503, "left": 0.882, "up": 1.586, "down": 1.09, "x": 0.0, "y": 0.0, "z": 1.09, "yaw": 0.0}, {"front": 3.079, "back": 1.092, "right": 2.503, "left": 0.882, "up": 1.586, "down": 1.09, "x": 0.0, "y": 0.0, "z": 1.09, "yaw": 0.0}, {"front": 3.079, "back": 1.092, "right": 2.503, "left": 0.882, "up": 1.586, "down": 1.09, "x": 0.0, "y": 0.0, "z": 1.09, "yaw": 0.0}, {"front": 3.079, "back": 1.092, "right": 2.503, "left": 0.901, "up": 1.585, "down": 1.09, "x": 0.0, "y": 0.0, "z": 1.09, "yaw": 0.0}, {"front": 3.079, "back": 1.092, "right": 2.497, "left": 0.901, "up": 1.585, "down": 1.09, "x": 0.0, "y": 0.0, "z": 1.09, "yaw": 0.0}, {"front": 3.079, "back": 1.092, "right": 2.497, "left": 0.901, "up": 1.585, "down": 1.085, "x": 0.0, "y": 0.0, "z": 1.085, "yaw": 0.0}, {"front": 3.079, "back": 1.092, "right": 2.497, "left": 0.901, "up": 1.585, "down": 1.085, "x": 0.0, "y": 0.0, "z": 1.085, "yaw": 0.0}, {"front": 3.079, "back": 1.092, "right": 2.497, "left": 0.901, "up": 1.585, "down": 1.085, "x": 0.0, "y": 0.0, "z": 1.085, "yaw": 0.0}, {"front": 3.079, "back": 1.092, "right": 2.497, "left": 0.901, "up": 1.585, "down": 1.085, "x": 0.0, "y": 0.0, "z": 1.085, "yaw": 0.0}, {"front": 3.079, "back": 1.092, "right": 2.497, "left": 0.901, "up": 1.585, "down": 1.085, "x": 0.0, "y": 0.0, "z": 1.085, "yaw": 0.0}, {"front": 3.079, "back": 1.092, "right": 2.497, "left": 0.901, "up": 1.585, "down": 1.085, "x": 0.0, "y": 0.0, "z": 1.085, "yaw": 0.0}, {"front": 3.092, "back": 1.092, "right": 2.497, "left": 0.901, "up": 1.585, "down": 1.085, "x": 0.0, "y": 0.0, "z": 1.085, "yaw": 0.0}, {"front": 3.092, "back": 1.092, "right": 2.497, "left": 0.901, "up": 1.585, "down": 1.085, "x": 0.0, "y": 0.0, "z": 1.085, "yaw": 0.0}, {"front": 3.092, "back": 1.092, "right": 2.497, "left": 0.954, "up": 1.586, "down": 1.085, "x": 0.0, "y": 0.0, "z": 1.085, "yaw": 0.0}, {"front": 3.092, "back": 1.092, "right": 2.5, "left": 0.954, "up": 1.586, "down": 1.085, "x": 0.0, "y": 0.0, "z": 1.085, "yaw": 0.0}, {"front": 3.092, "back": 1.092, "right": 2.5, "left": 0.954, "up": 1.586, "down": 1.081, "x": 0.0, "y": 0.0, "z": 1.081, "yaw": 0.0}, {"front": 3.092, "back": 1.092, "right": 2.5, "left": 0.954, "up": 1.586, "down": 1.081, "x": 0.0, "y": 0.0, "z": 1.081, "yaw": 0.0}, {"front": 3.092, "back": 1.092, "right": 2.5, "left": 0.954, "up": 1.586, "down": 1.081, "x": 0.0, "y": 0.0, "z": 1.081, "yaw": 0.0}, {"front": 3.092, "back": 1.092, "right": 2.5, "left": 0.954, "up": 1.586, "down": 1.081, "x": 0.0, "y": 0.0, "z": 1.081, "yaw": 0.0}, {"front": 3.092, "back": 1.092, "right": 2.5, "left": 0.954, "up": 1.586, "down": 1.086, "x": 0.0, "y": 0.0, "z": 1.086, "yaw": 0.0}, {"front": 3.092, "back": 1.092, "right": 2.5, "left": 0.954, "up": 1.586, "down": 1.086, "x": 0.0, "y": 0.0, "z": 1.086, "yaw": 0.0}, {"front": 3.085, "back": 1.092, "right": 2.5, "left": 0.954, "up": 1.586, "down": 1.086, "x": 0.0, "y": 0.0, "z": 1.086, "yaw": 0.0}, {"front": 3.085, "back": 1.091, "right": 2.5, "left": 0.954, "up": 1.586, "down": 1.086, "x": 0.0, "y": 0.0, "z": 1.086, "yaw": 0.0}, {"front": 3.085, "back": 1.091, "right": 2.5, "left": 32.766, "up": 1.585, "down": 1.086, "x": 0.0, "y": 0.0, "z": 1.086, "yaw": 0.0}, {"front": 3.085, "back": 1.091, "right": 2.51, "left": 32.766, "up": 1.585, "down": 1.086, "x": 0.0, "y": 0.0, "z": 1.086, "yaw": 0.0}, {"front": 3.085, "back": 1.091, "right": 2.51, "left": 32.766, "up": 1.585, "down": 1.075, "x": 0.0, "y": 0.0, "z": 1.075, "yaw": 0.0}, {"front": 3.085, "back": 1.091, "right": 2.51, "left": 32.766, "up": 1.585, "down": 1.075, "x": 0.0, "y": 0.0, "z": 1.075, "yaw": 0.0}, {"front": 3.085, "back": 1.091, "right": 2.51, "left": 32.766, "up": 1.585, "down": 1.075, "x": 0.0, "y": 0.0, "z": 1.075, "yaw": 0.0}, {"front": 3.085, "back": 1.091, "right": 2.51, "left": 32.766, "up": 1.585, "down": 1.075, "x": 0.0, "y": 0.0, "z": 1.075, "yaw": 0.0}, {"front": 3.085, "back": 1.091, "right": 2.51, "left": 32.766, "up": 1.585, "down": 1.078, "x": 0.0, "y": 0.0, "z": 1.078, "yaw": 0.0}, {"front": 3.085, "back": 1.091, "right": 2.51, "left": 32.766, "up": 1.585, "down": 1.078, "x": 0.0, "y": 0.0, "z": 1.078, "yaw": 0.0}, {"front": 3.1, "back": 1.091, "right": 2.51, "left": 32.766, "up": 1.585, "down": 1.078, "x": 0.0, "y": 0.0, "z": 1.078, "yaw": 0.0}, {"front": 3.1, "back": 1.074, "right": 2.51, "left": 32.766, "up": 1.585, "down": 1.078, "x": 0.0, "y": 0.0, "z": 1.078, "yaw": 0.0}, {"front": 3.1, "back": 1.074, "right": 2.51, "left": 0.83, "up": 1.588, "down": 1.078, "x": 0.0, "y": 0.0, "z": 1.078, "yaw": 0.0}, {"front": 3.1, "back": 1.074, "right": 2.527, "left": 0.83, "up": 1.588, "down": 1.078, "x": 0.0, "y": 0.0, "z": 1.078, "yaw": 0.0}, {"front": 3.1, "back": 1.074, "right": 2.527, "left": 0.83, "up": 1.588, "down": 1.082, "x": 0.0, "y": 0.0, "z": 1.082, "yaw": 0.0}, {"front": 3.1, "back": 1.074, "right": 2.527, "left": 0.83, "up": 1.588, "down": 1.082, "x": 0.0, "y": 0.0, "z": 1.082, "yaw": 0.0}, {"front": 3.1, "back": 1.074, "right": 2.527, "left": 0.83, "up": 1.588, "down": 1.082, "x": 0.0, "y": 0.0, "z": 1.082, "yaw": 0.0}, {"front": 3.1, "back": 1.074, "right": 2.527, "left": 0.83, "up": 1.588, "down": 1.082, "x": 0.0, "y": 0.0, "z": 1.082, "yaw": 0.0}, {"front": 3.1, "back": 1.074, "right": 2.527, "left": 0.83, "up": 1.588, "down": 1.082, "x": 0.0, "y": 0.0, "z": 1.082, "yaw": 0.0}, {"front": 3.1, "back": 1.074, "right": 2.527, "left": 0.83, "up": 1.588, "down": 1.082, "x": 0.0, "y": 0.0, "z": 1.082, "yaw": 0.0}, {"front": 32.766, "back": 1.074, "right": 2.527, "left": 0.83, "up": 1.588, "down": 1.082, "x": 0.0, "y": 0.0, "z": 1.082, "yaw": 0.0}, {"front": 32.766, "back": 1.076, "right": 2.527, "left": 0.83, "up": 1.588, "down": 1.082, "x": 0.0, "y": 0.0, "z": 1.082, "yaw": 0.0}, {"front": 32.766, "back": 1.076, "right": 2.527, "left": 0.801, "up": 1.591, "down": 1.082, "x": 0.0, "y": 0.0, "z": 1.082, "yaw": 0.0}, {"front": 32.766, "back": 1.076, "right": 2.531, "left": 0.801, "up": 1.591, "down": 1.082, "x": 0.0, "y": 0.0, "z": 1.082, "yaw": 0.0}, {"front": 32.766, "back": 1.076, "right": 2.531, "left": 0.801, "up": 1.591, "down": 1.086, "x": 0.0, "y": 0.0, "z": 1.086, "yaw": 0.0}, {"front": 32.766, "back": 1.076, "right": 2.531, "left": 0.801, "up": 1.591, "down": 1.086, "x": 0.0, "y": 0.0, "z": 1.086, "yaw": 0.0}, {"front": 32.766, "back": 1.076, "right": 2.531, "left": 0.801, "up": 1.591, "down": 1.086, "x": 0.0, "y": 0.0, "z": 1.086, "yaw": 0.0}, {"front": 32.766, "back": 1.076, "right": 2.531, "left": 0.801, "up": 1.591, "down": 1.086, "x": 0.0, "y": 0.0, "z": 1.086, "yaw": 0.0}, {"front": 32.766, "back": 1.076, "right": 2.531, "left": 0.801, "up": 1.591, "down": 1.088, "x": 0.0, "y": 0.0, "z": 1.088, "yaw": 0.0}, {"front": 32.766, "back": 1.076, "right": 2.531, "left": 0.801, "up": 1.591, "down": 1.088, "x": 0.0, "y": 0.0, "z": 1.088, "yaw": 0.0}, {"front": 3.1, "back": 1.076, "right": 2.531, "left": 0.801, "up": 1.591, "down": 1.088, "x": 0.0, "y": 0.0, "z": 1.088, "yaw": 0.0}, {"front": 3.1, "back": 1.066, "right": 2.531, "left": 0.801, "up": 1.591, "down": 1.088, "x": 0.0, "y": 0.0, "z": 1.088, "yaw": 0.0}, {"front": 3.1, "back": 1.066, "right": 2.531, "left": 0.809, "up": 1.586, "down": 1.088, "x": 0.0, "y": 0.0, "z": 1.088, "yaw": 0.0}, {"front": 3.1, "back": 1.066, "right": 2.524, "left": 0.809, "up": 1.586, "down": 1.088, "x": 0.0, "y": 0.0, "z": 1.088, "yaw": 0.0}, {"front": 3.1, "back": 1.066, "right": 2.524, "left": 0.809, "up": 1.586, "down": 1.087, "x": 0.0, "y": 0.0, "z": 1.087, "yaw": 0.0}, {"front": 3.1, "back": 1.066, "right": 2.524, "left": 0.809, "up": 1.586, "down": 1.087, "x": 0.0, "y": 0.0, "z": 1.087, "yaw": 0.0}, {"front": 3.1, "back": 1.066, "right": 2.524, "left": 0.809, "up": 1.586, "down": 1.087, "x": 0.0, "y": 0.0, "z": 1.087, "yaw": 0.0}, {"front": 3.1, "back": 1.066, "right": 2.524, "left": 0.809, "up": 1.586, "down": 1.087, "x": 0.0, "y": 0.0, "z": 1.087, "yaw": 0.0}, {"front": 3.1, "back": 1.066, "right": 2.524, "left": 0.809, "up": 1.586, "down": 1.088, "x": 0.0, "y": 0.0, "z": 1.088, "yaw": 0.0}, {"front": 3.1, "back": 1.066, "right": 2.524, "left": 0.809, "up": 1.586, "down": 1.088, "x": 0.0, "y": 0.0, "z": 1.088, "yaw": 0.0}, {"front": 32.766, "back": 1.066, "right": 2.524, "left": 0.809, "up": 1.586, "down": 1.088, "x": 0.0, "y": 0.0, "z": 1.088, "yaw": 0.0}, {"front": 32.766, "back": 1.063, "right": 2.524, "left": 0.809, "up": 1.586, "down": 1.088, "x": 0.0, "y": 0.0, "z": 1.088, "yaw": 0.0}, {"front": 32.766, "back": 1.063, "right": 2.524, "left": 0.819, "up": 1.59, "down": 1.088, "x": 0.0, "y": 0.0, "z": 1.088, "yaw": 0.0}, {"front": 32.766, "back": 1.063, "right": 2.527, "left": 0.819, "up": 1.59, "down": 1.088, "x": 0.0, "y": 0.0, "z": 1.088, "yaw": 0.0}, {"front": 32.766, "back": 1.063, "right": 2.527, "left": 0.819, "up": 1.59, "down": 1.079, "x": 0.0, "y": 0.0, "z": 1.079, "yaw": 0.0}, {"front": 32.766, "back": 1.063, "right": 2.527, "left": 0.819, "up": 1.59, "down": 1.079, "x": 0.0, "y": 0.0, "z": 1.079, "yaw": 0.0}, {"front": 32.766, "back": 1.063, "right": 2.527, "left": 0.819, "up": 1.59, "down": 1.079, "x": 0.0, "y": 0.0, "z": 1.079, "yaw": 0.0}, {"front": 32.766, "back": 1.063, "right": 2.527, "left": 0.819, "up": 1.59, "down": 1.079, "x": 0.0, "y": 0.0, "z": 1.079, "yaw": 0.0}, {"front": 32.766, "back": 1.063, "right": 2.527, "left": 0.819, "up": 1.59, "down": 1.086, "x": 0.0, "y": 0.0, "z": 1.086, "yaw": 0.0}, {"front": 32.766, "back": 1.063, "right": 2.527, "left": 0.819, "up": 1.59, "down": 1.086, "x": 0.0, "y": 0.0, "z": 1.086, "yaw": 0.0}, {"front": 32.766, "back": 1.063, "right": 2.527, "left": 0.819, "up": 1.59, "down": 1.086, "x": 0.0, "y": 0.0, "z": 1.086, "yaw": 0.0}, {"front": 32.766, "back": 1.055, "right": 2.527, "left": 0.819, "up": 1.59, "down": 1.086, "x": 0.0, "y": 0.0, "z": 1.086, "yaw": 0.0}, {"front": 32.766, "back": 1.055, "right": 2.527, "left": 0.813, "up": 1.589, "down": 1.086, "x": 0.0, "y": 0.0, "z": 1.086, "yaw": 0.0}, {"front": 32.766, "back": 1.055, "right": 2.51, "left": 0.813, "up": 1.589, "down": 1.086, "x": 0.0, "y": 0.0, "z": 1.086, "yaw": 0.0}, {"front": 32.766, "back": 1.055, "right": 2.51, "left": 0.813, "up": 1.589, "down": 1.087, "x": 0.0, "y": 0.0, "z": 1.087, "yaw": 0.0}, {"front": 32.766, "back": 1.055, "right": 2.51, "left": 0.813, "up": 1.589, "down": 1.087, "x": 0.0, "y": 0.0, "z": 1.087, "yaw": 0.0}, {"front": 32.766, "back": 1.055, "right": 2.51, "left": 0.813, "up": 1.589, "down": 1.087, "x": 0.0, "y": 0.0, "z": 1.087, "yaw": 0.0}, {"front": 32.766, "back": 1.055, "right": 2.51, "left": 0.813, "up": 1.589, "down": 1.087, "x": 0.0, "y": 0.0, "z": 1.087, "yaw": 0.0}, {"front": 32.766, "back": 1.055, "right": 2.51, "left": 0.813, "up": 1.589, "down": 1.085, "x": 0.0, "y": 0.0, "z": 1.085, "yaw": 0.0}, {"front": 32.766, "back": 1.055, "right": 2.51, "left": 0.813, "up": 1.589, "down": 1.085, "x": 0.0, "y": 0.0, "z": 1.085, "yaw": 0.0}, {"front": 3.069, "back": 1.055, "right": 2.51, "left": 0.813, "up": 1.589, "down": 1.085, "x": 0.0, "y": 0.0, "z": 1.085, "yaw": 0.0}, {"front": 3.069, "back": 1.059, "right": 2.51, "left": 0.813, "up": 1.589, "down": 1.085, "x": 0.0, "y": 0.0, "z": 1.085, "yaw": 0.0}, {"front": 3.069, "back": 1.059, "right": 2.51, "left": 0.843, "up": 1.582, "down": 1.085, "x": 0.0, "y": 0.0, "z": 1.085, "yaw": 0.0}, {"front": 3.069, "back": 1.059, "right": 2.494, "left": 0.843, "up": 1.582, "down": 1.085, "x": 0.0, "y": 0.0, "z": 1.085, "yaw": 0.0}, {"front": 3.069, "back": 1.059, "right": 2.494, "left": 0.843, "up": 1.582, "down": 1.079, "x": 0.0, "y": 0.0, "z": 1.079, "yaw": 0.0}, {"front": 3.069, "back": 1.059, "right": 2.494, "left": 0.843, "up": 1.582, "down": 1.079, "x": 0.0, "y": 0.0, "z": 1.079, "yaw": 0.0}, {"front": 3.069, "back": 1.059, "right": 2.494, "left": 0.843, "up": 1.582, "down": 1.079, "x": 0.0, "y": 0.0, "z": 1.079, "yaw": 0.0}, {"front": 3.069, "back": 1.059, "right": 2.494, "left": 0.843, "up": 1.582, "down": 1.079, "x": 0.0, "y": 0.0, "z": 1.079, "yaw": 0.0}, {"front": 3.069, "back": 1.059, "right": 2.494, "left": 0.843, "up": 1.582, "down": 1.081, "x": 0.0, "y": 0.0, "z": 1.081, "yaw": 0.0}, {"front": 3.069, "back": 1.059, "right": 2.494, "left": 0.843, "up": 1.582, "down": 1.081, "x": 0.0, "y": 0.0, "z": 1.081, "yaw": 0.0}, {"front": 32.766, "back": 1.059, "right": 2.494, "left": 0.843, "up": 1.582, "down": 1.081, "x": 0.0, "y": 0.0, "z": 1.081, "yaw": 0.0}, {"front": 32.766, "back": 1.071, "right": 2.494, "left": 0.843, "up": 1.582, "down": 1.081, "x": 0.0, "y": 0.0, "z": 1.081, "yaw": 0.0}, {"front": 32.766, "back": 1.071, "right": 2.494, "left": 0.855, "up": 1.592, "down": 1.081, "x": 0.0, "y": 0.0, "z": 1.081, "yaw": 0.0}, {"front": 32.766, "back": 1.071, "right": 2.49, "left": 0.855, "up": 1.592, "down": 1.081, "x": 0.0, "y": 0.0, "z": 1.081, "yaw": 0.0}, {"front": 32.766, "back": 1.071, "right": 2.49, "left": 0.855, "up": 1.592, "down": 1.089, "x": 0.0, "y": 0.0, "z": 1.089, "yaw": 0.0}, {"front": 32.766, "back": 1.071, "right": 2.49, "left": 0.855, "up": 1.592, "down": 1.089, "x": 0.0, "y": 0.0, "z": 1.089, "yaw": 0.0}, {"front": 32.766, "back": 1.071, "right": 2.49, "left": 0.855, "up": 1.592, "down": 1.089, "x": 0.0, "y": 0.0, "z": 1.089, "yaw": 0.0}, {"front": 32.766, "back": 1.071, "right": 2.49, "left": 0.855, "up": 1.592, "down": 1.089, "x": 0.0, "y": 0.0, "z": 1.089, "yaw": 0.0}, {"front": 32.766, "back": 1.071, "right": 2.49, "left": 0.855, "up": 1.592, "down": 1.088, "x": 0.0, "y": 0.0, "z": 1.088, "yaw": 0.0}, {"front": 32.766, "back": 1.071, "right": 2.49, "left": 0.855, "up": 1.592, "down": 1.088, "x": 0.0, "y": 0.0, "z": 1.088, "yaw": 0.0}, {"front": 3.051, "back": 1.071, "right": 2.49, "left": 0.855, "up": 1.592, "down": 1.088, "x": 0.0, "y": 0.0, "z": 1.088, "yaw": 0.0}, {"front": 3.051, "back": 1.062, "right": 2.49, "left": 0.855, "up": 1.592, "down": 1.088, "x": 0.0, "y": 0.0, "z": 1.088, "yaw": 0.0}, {"front": 3.051, "back": 1.062, "right": 2.49, "left": 0.899, "up": 1.598, "down": 1.088, "x": 0.0, "y": 0.0, "z": 1.088, "yaw": 0.0}, {"front": 3.051, "back": 1.062, "right": 2.495, "left": 0.899, "up": 1.598, "down": 1.088, "x": 0.0, "y": 0.0, "z": 1.088, "yaw": 0.0}, {"front": 3.051, "back": 1.062, "right": 2.495, "left": 0.899, "up": 1.598, "down": 1.085, "x": 0.0, "y": 0.0, "z": 1.085, "yaw": 0.0}, {"front": 3.051, "back": 1.062, "right": 2.495, "left": 0.899, "up": 1.598, "down": 1.085, "x": 0.0, "y": 0.0, "z": 1.085, "yaw": 0.0}, {"front": 3.051, "back": 1.062, "right": 2.495, "left": 0.899, "up": 1.598, "down": 1.085, "x": 0.0, "y": 0.0, "z": 1.085, "yaw": 0.0}, {"front": 3.051, "back": 1.062, "right": 2.495, "left": 0.899, "up": 1.598, "down": 1.085, "x": 0.0, "y": 0.0, "z": 1.085, "yaw": 0.0}, {"front": 3.051, "back": 1.062, "right": 2.495, "left": 0.899, "up": 1.598, "down": 1.085, "x": 0.0, "y": 0.0, "z": 1.085, "yaw": 0.0}, {"front": 3.051, "back": 1.062, "right": 2.495, "left": 0.899, "up": 1.598, "down": 1.085, "x": 0.0, "y": 0.0, "z": 1.085, "yaw": 0.0}, {"front": 32.766, "back": 1.062, "right": 2.495, "left": 0.899, "up": 1.598, "down": 1.085, "x": 0.0, "y": 0.0, "z": 1.085, "yaw": 0.0}, {"front": 32.766, "back": 1.06, "right": 2.495, "left": 0.899, "up": 1.598, "down": 1.085, "x": 0.0, "y": 0.0, "z": 1.085, "yaw": 0.0}, {"front": 32.766, "back": 1.06, "right": 2.495, "left": 0.897, "up": 1.603, "down": 1.085, "x": 0.0, "y": 0.0, "z": 1.085, "yaw": 0.0}, {"front": 32.766, "back": 1.06, "right": 2.494, "left": 0.897, "up": 1.603, "down": 1.085, "x": 0.0, "y": 0.0, "z": 1.085, "yaw": 0.0}, {"front": 32.766, "back": 1.06, "right": 2.494, "left": 0.897, "up": 1.603, "down": 1.084, "x": 0.0, "y": 0.0, "z": 1.084, "yaw": 0.0}, {"front": 32.766, "back": 1.06, "right": 2.494, "left": 0.897, "up": 1.603, "down": 1.084, "x": 0.0, "y": 0.0, "z": 1.084, "yaw": 0.0}, {"front": 32.766, "back": 1.06, "right": 2.494, "left": 0.897, "up": 1.603, "down": 1.084, "x": 0.0, "y": 0.0, "z": 1.084, "yaw": 0.0}, {"front": 32.766, "back": 1.06, "right": 2.494, "left": 0.897, "up": 1.603, "down": 1.084, "x": 0.0, "y": 0.0, "z": 1.084, "yaw": 0.0}, {"front": 32.766, "back": 1.06, "right": 2.494, "left": 0.897, "up": 1.603, "down": 1.081, "x": 0.0, "y": 0.0, "z": 1.081, "yaw": 0.0}, {"front": 32.766, "back": 1.06, "right": 2.494, "left": 0.897, "up": 1.603, "down": 1.081, "x": 0.0, "y": 0.0, "z": 1.081, "yaw": 0.0}, {"front": 3.08, "back": 1.06, "right": 2.494, "left": 0.897, "up": 1.603, "down": 1.081, "x": 0.0, "y": 0.0, "z": 1.081, "yaw": 0.0}, {"front": 3.08, "back": 1.058, "right": 2.494, "left": 0.897, "up": 1.603, "down": 1.081, "x": 0.0, "y": 0.0, "z": 1.081, "yaw": 0.0}, {"front": 3.08, "back": 1.058, "right": 2.494, "left": 0.877, "up": 1.597, "down": 1.081, "x": 0.0, "y": 0.0, "z": 1.081, "yaw": 0.0}, {"front": 3.08, "back": 1.058, "right": 2.495, "left": 0.877, "up": 1.597, "down": 1.081, "x": 0.0, "y": 0.0, "z": 1.081, "yaw": 0.0}, {"front": 3.08, "back": 1.058, "right": 2.495, "left": 0.877, "up": 1.597, "down": 1.078, "x": 0.0, "y": 0.0, "z": 1.078, "yaw": 0.0}, {"front": 3.08, "back": 1.058, "right": 2.495, "left": 0.877, "up": 1.597, "down": 1.078, "x": 0.0, "y": 0.0, "z": 1.078, "yaw": 0.0}, {"front": 3.08, "back": 1.058, "right": 2.495, "left": 0.877, "up": 1.597, "down": 1.078, "x": 0.0, "y": 0.0, "z": 1.078, "yaw": 0.0}, {"front": 3.08, "back": 1.058, "right": 2.495, "left": 0.877, "up": 1.597, "down": 1.078, "x": 0.0, "y": 0.0, "z": 1.078, "yaw": 0.0}, {"front": 3.08, "back": 1.058, "right": 2.495, "left": 0.877, "up": 1.597, "down": 1.073, "x": 0.0, "y": 0.0, "z": 1.073, "yaw": 0.0}, {"front": 3.08, "back": 1.058, "right": 2.495, "left": 0.877, "up": 1.597, "down": 1.073, "x": 0.0, "y": 0.0, "z": 1.073, "yaw": 0.0}, {"front": 32.766, "back": 1.058, "right": 2.495, "left": 0.877, "up": 1.597, "down": 1.073, "x": 0.0, "y": 0.0, "z": 1.073, "yaw": 0.0}, {"front": 32.766, "back": 1.103, "right": 2.495, "left": 0.877, "up": 1.597, "down": 1.073, "x": 0.0, "y": 0.0, "z": 1.073, "yaw": 0.0}, {"front": 32.766, "back": 1.103, "right": 2.495, "left": 32.766, "up": 1.598, "down": 1.073, "x": 0.0, "y": 0.0, "z": 1.073, "yaw": 0.0}, {"front": 32.766, "back": 1.103, "right": 2.5, "left": 32.766, "up": 1.598, "down": 1.073, "x": 0.0, "y": 0.0, "z": 1.073, "yaw": 0.0}, {"front": 32.766, "back": 1.103, "right": 2.5, "left": 32.766, "up": 1.598, "down": 1.075, "x": 0.0, "y": 0.0, "z": 1.075, "yaw": 0.0}, {"front": 32.766, "back": 1.103, "right": 2.5, "left": 32.766, "up": 1.598, "down": 1.075, "x": 0.0, "y": 0.0, "z": 1.075, "yaw": 0.0}, {"front": 32.766, "back": 1.103, "right": 2.5, "left": 32.766, "up": 1.598, "down": 1.075, "x": 0.0, "y": 0.0, "z": 1.075, "yaw": 0.0}, {"front": 32.766, "back": 1.103, "right": 2.5, "left": 32.766, "up": 1.598, "down": 1.075, "x": 0.0, "y": 0.0, "z": 1.075, "yaw": 0.0}, {"front": 32.766, "back": 1.103, "right": 2.5, "left": 32.766, "up": 1.598, "down": 1.07, "x": 0.0, "y": 0.0, "z": 1.07, "yaw": 0.0}, {"front": 32.766, "back": 1.103, "right": 2.5, "left": 32.766, "up": 1.598, "down": 1.07, "x": 0.0, "y": 0.0, "z": 1.07, "yaw": 0.0}, {"front": 32.766, "back": 1.103, "right": 2.5, "left": 32.766, "up": 1.598, "down": 1.07, "x": 0.0, "y": 0.0, "z": 1.07, "yaw": 0.0}, {"front": 32.766, "back": 1.104, "right": 2.5, "left": 32.766, "up": 1.598, "down": 1.07, "x": 0.0, "y": 0.0, "z": 1.07, "yaw": 0.0}, {"front": 32.766, "back": 1.104, "right": 2.5, "left": 0.851, "up": 1.598, "down": 1.07, "x": 0.0, "y": 0.0, "z": 1.07, "yaw": 0.0}, {"front": 32.766, "back": 1.104, "right": 2.516, "left": 0.851, "up": 1.598, "down": 1.07, "x": 0.0, "y": 0.0, "z": 1.07, "yaw": 0.0}, {"front": 32.766, "back": 1.104, "right": 2.516, "left": 0.851, "up": 1.598, "down": 1.068, "x": 0.0, "y": 0.0, "z": 1.068, "yaw": 0.0}, {"front": 32.766, "back": 1.104, "right": 2.516, "left": 0.851, "up": 1.598, "down": 1.068, "x": 0.0, "y": 0.0, "z": 1.068, "yaw": 0.0}, {"front": 32.766, "back": 1.104, "right": 2.516, "left": 0.851, "up": 1.598, "down": 1.068, "x": 0.0, "y": 0.0, "z": 1.068, "yaw": 0.0}, {"front": 32.766, "back": 1.104, "right": 2.516, "left": 0.851, "up": 1.598, "down": 1.068, "x": 0.0, "y": 0.0, "z": 1.068, "yaw": 0.0}, {"front": 32.766, "back": 1.104, "right": 2.516, "left": 0.851, "up": 1.598, "down": 1.074, "x": 0.0, "y": 0.0, "z": 1.074, "yaw": 0.0}, {"front": 32.766, "back": 1.104, "right": 2.516, "left": 0.851, "up": 1.598, "down": 1.074, "x": 0.0, "y": 0.0, "z": 1.074, "yaw": 0.0}, {"front": 3.083, "back": 1.104, "right": 2.516, "left": 0.851, "up": 1.598, "down": 1.074, "x": 0.0, "y": 0.0, "z": 1.074, "yaw": 0.0}, {"front": 3.083, "back": 1.085, "right": 2.516, "left": 0.851, "up": 1.598, "down": 1.074, "x": 0.0, "y": 0.0, "z": 1.074, "yaw": 0.0}, {"front": 3.083, "back": 1.085, "right": 2.516, "left": 0.793, "up": 1.603, "down": 1.074, "x": 0.0, "y": 0.0, "z": 1.074, "yaw": 0.0}, {"front": 3.083, "back": 1.085, "right": 2.536, "left": 0.793, "up": 1.603, "down": 1.074, "x": 0.0, "y": 0.0, "z": 1.074, "yaw": 0.0}, {"front": 3.083, "back": 1.085, "right": 2.536, "left": 0.793, "up": 1.603, "down": 1.066, "x": 0.0, "y": 0.0, "z": 1.066, "yaw": 0.0}, {"front": 3.083, "back": 1.085, "right": 2.536, "left": 0.793, "up": 1.603, "down": 1.066, "x": 0.0, "y": 0.0, "z": 1.066, "yaw": 0.0}, {"front": 3.083, "back": 1.085, "right": 2.536, "left": 0.793, "up": 1.603, "down": 1.066, "x": 0.0, "y": 0.0, "z": 1.066, "yaw": 0.0}, {"front": 3.083, "back": 1.085, "right": 2.536, "left": 0.793, "up": 1.603, "down": 1.066, "x": 0.0, "y": 0.0, "z": 1.066, "yaw": 0.0}, {"front": 3.083, "back": 1.085, "right": 2.536, "left": 0.793, "up": 1.603, "down": 1.074, "x": 0.0, "y": 0.0, "z": 1.074, "yaw": 0.0}, {"front": 3.083, "back": 1.085, "right": 2.536, "left": 0.793, "up": 1.603, "down": 1.074, "x": 0.0, "y": 0.0, "z": 1.074, "yaw": 0.0}, {"front": 3.096, "back": 1.085, "right": 2.536, "left": 0.793, "up": 1.603, "down": 1.074, "x": 0.0, "y": 0.0, "z": 1.074, "yaw": 0.0}, {"front": 3.096, "back": 1.076, "right": 2.536, "left": 0.793, "up": 1.603, "down": 1.074, "x": 0.0, "y": 0.0, "z": 1.074, "yaw": 0.0}, {"front": 3.096, "back": 1.076, "right": 2.536, "left": 0.795, "up": 1.605, "down": 1.074, "x": 0.0, "y": 0.0, "z": 1.074, "yaw": 0.0}, {"front": 3.096, "back": 1.076, "right": 2.53, "left": 0.795, "up": 1.605, "down": 1.074, "x": 0.0, "y": 0.0, "z": 1.074, "yaw": 0.0}, {"front": 3.096, "back": 1.076, "right": 2.53, "left": 0.795, "up": 1.605, "down": 1.074, "x": 0.0, "y": 0.0, "z": 1.074, "yaw": 0.0}, {"front": 3.096, "back": 1.076, "right": 2.53, "left": 0.795, "up": 1.605, "down": 1.074, "x": 0.0, "y": 0.0, "z": 1.074, "yaw": 0.0}, {"front": 3.096, "back": 1.076, "right": 2.53, "left": 0.795, "up": 1.605, "down": 1.074, "x": 0.0, "y": 0.0, "z": 1.074, "yaw": 0.0}, {"front": 3.096, "back": 1.076, "right": 2.53, "left": 0.795, "up": 1.605, "down": 1.074, "x": 0.0, "y": 0.0, "z": 1.074, "yaw": 0.0}, {"front": 3.096, "back": 1.076, "right": 2.53, "left": 0.795, "up": 1.605, "down": 1.078, "x": 0.0, "y": 0.0, "z": 1.078, "yaw": 0.0}, {"front": 3.096, "back": 1.076, "right": 2.53, "left": 0.795, "up": 1.605, "down": 1.078, "x": 0.0, "y": 0.0, "z": 1.078, "yaw": 0.0}, {"front": 32.766, "back": 1.076, "right": 2.53, "left": 0.795, "up": 1.605, "down": 1.078, "x": 0.0, "y": 0.0, "z": 1.078, "yaw": 0.0}, {"front": 32.766, "back": 1.076, "right": 2.53, "left": 0.795, "up": 1.605, "down": 1.078, "x": 0.0, "y": 0.0, "z": 1.078, "yaw": 0.0}, {"front": 32.766, "back": 1.076, "right": 2.53, "left": 0.797, "up": 1.606, "down": 1.078, "x": 0.0, "y": 0.0, "z": 1.078, "yaw": 0.0}, {"front": 32.766, "back": 1.076, "right": 2.528, "left": 0.797, "up": 1.606, "down": 1.078, "x": 0.0, "y": 0.0, "z": 1.078, "yaw": 0.0}, {"front": 32.766, "back": 1.076, "right": 2.528, "left": 0.797, "up": 1.606, "down": 1.075, "x": 0.0, "y": 0.0, "z": 1.075, "yaw": 0.0}, {"front": 32.766, "back": 1.076, "right": 2.528, "left": 0.797, "up": 1.606, "down": 1.075, "x": 0.0, "y": 0.0, "z": 1.075, "yaw": 0.0}, {"front": 32.766, "back": 1.076, "right": 2.528, "left": 0.797, "up": 1.606, "down": 1.075, "x": 0.0, "y": 0.0, "z": 1.075, "yaw": 0.0}, {"front": 32.766, "back": 1.076, "right": 2.528, "left": 0.797, "up": 1.606, "down": 1.075, "x": 0.0, "y": 0.0, "z": 1.075, "yaw": 0.0}, {"front": 32.766, "back": 1.076, "right": 2.528, "left": 0.797, "up": 1.606, "down": 1.077, "x": 0.0, "y": 0.0, "z": 1.077, "yaw": 0.0}, {"front": 32.766, "back": 1.076, "right": 2.528, "left": 0.797, "up": 1.606, "down": 1.077, "x": 0.0, "y": 0.0, "z": 1.077, "yaw": 0.0}, {"front": 3.079, "back": 1.076, "right": 2.528, "left": 0.797, "up": 1.606, "down": 1.077, "x": 0.0, "y": 0.0, "z": 1.077, "yaw": 0.0}, {"front": 3.079, "back": 1.074, "right": 2.528, "left": 0.797, "up": 1.606, "down": 1.077, "x": 0.0, "y": 0.0, "z": 1.077, "yaw": 0.0}, {"front": 3.079, "back": 1.074, "right": 2.528, "left": 0.79, "up": 1.6, "down": 1.077, "x": 0.0, "y": 0.0, "z": 1.077, "yaw": 0.0}, {"front": 3.079, "back": 1.074, "right": 2.531, "left": 0.79, "up": 1.6, "down": 1.077, "x": 0.0, "y": 0.0, "z": 1.077, "yaw": 0.0}, {"front": 3.079, "back": 1.074, "right": 2.531, "left": 0.79, "up": 1.6, "down": 1.071, "x": 0.0, "y": 0.0, "z": 1.071, "yaw": 0.0}, {"front": 3.079, "back": 1.074, "right": 2.531, "left": 0.79, "up": 1.6, "down": 1.071, "x": 0.0, "y": 0.0, "z": 1.071, "yaw": 0.0}, {"front": 3.079, "back": 1.074, "right": 2.531, "left": 0.79, "up": 1.6, "down": 1.071, "x": 0.0, "y": 0.0, "z": 1.071, "yaw": 0.0}, {"front": 3.079, "back": 1.074, "right": 2.531, "left": 0.79, "up": 1.6, "down": 1.071, "x": 0.0, "y": 0.0, "z": 1.071, "yaw": 0.0}, {"front": 3.079, "back": 1.074, "right": 2.531, "left": 0.79, "up": 1.6, "down": 1.068, "x": 0.0, "y": 0.0, "z": 1.068, "yaw": 0.0}, {"front": 3.079, "back": 1.074, "right": 2.531, "left": 0.79, "up": 1.6, "down": 1.068, "x": 0.0, "y": 0.0, "z": 1.068, "yaw": 0.0}, {"front": 3.087, "back": 1.074, "right": 2.531, "left": 0.79, "up": 1.6, "down": 1.068, "x": 0.0, "y": 0.0, "z": 1.068, "yaw": 0.0}, {"front": 3.087, "back": 1.077, "right": 2.531, "left": 0.79, "up": 1.6, "down": 1.068, "x": 0.0, "y": 0.0, "z": 1.068, "yaw": 0.0}, {"front": 3.087, "back": 1.077, "right": 2.531, "left": 0.786, "up": 1.603, "down": 1.068, "x": 0.0, "y": 0.0, "z": 1.068, "yaw": 0.0}, {"front": 3.087, "back": 1.077, "right": 2.538, "left": 0.786, "up": 1.603, "down": 1.068, "x": 0.0, "y": 0.0, "z": 1.068, "yaw": 0.0}, {"front": 3.087, "back": 1.077, "right": 2.538, "left": 0.786, "up": 1.603, "down": 1.065, "x": 0.0, "y": 0.0, "z": 1.065, "yaw": 0.0}, {"front": 3.087, "back": 1.077, "right": 2.538, "left": 0.786, "up": 1.603, "down": 1.065, "x": 0.0, "y": 0.0, "z": 1.065, "yaw": 0.0}, {"front": 3.087, "back": 1.077, "right": 2.538, "left": 0.786, "up": 1.603, "down": 1.065, "x": 0.0, "y": 0.0, "z": 1.065, "yaw": 0.0}, {"front": 3.087, "back": 1.077, "right": 2.538, "left": 0.786, "up": 1.603, "down": 1.065, "x": 0.0, "y": 0.0, "z": 1.065, "yaw": 0.0}, {"front": 3.087, "back": 1.077, "right": 2.538, "left": 0.786, "up": 1.603, "down": 1.064, "x": 0.0, "y": 0.0, "z": 1.064, "yaw": 0.0}, {"front": 3.087, "back": 1.077, "right": 2.538, "left": 0.786, "up": 1.603, "down": 1.064, "x": 0.0, "y": 0.0, "z": 1.064, "yaw": 0.0}, {"front": 3.092, "back": 1.077, "right": 2.538, "left": 0.786, "up": 1.603, "down": 1.064, "x": 0.0, "y": 0.0, "z": 1.064, "yaw": 0.0}, {"front": 3.092, "back": 1.088, "right": 2.538, "left": 0.786, "up": 1.603, "down": 1.064, "x": 0.0, "y": 0.0, "z": 1.064, "yaw": 0.0}, {"front": 3.092, "back": 1.088, "right": 2.538, "left": 0.797, "up": 1.603, "down": 1.064, "x": 0.0, "y": 0.0, "z": 1.064, "yaw": 0.0}, {"front": 3.092, "back": 1.088, "right": 2.521, "left": 0.797, "up": 1.603, "down": 1.064, "x": 0.0, "y": 0.0, "z": 1.064, "yaw": 0.0}, {"front": 3.092, "back": 1.088, "right": 2.521, "left": 0.797, "up": 1.603, "down": 1.064, "x": 0.0, "y": 0.0, "z": 1.064, "yaw": 0.0}, {"front": 3.092, "back": 1.088, "right": 2.521, "left": 0.797, "up": 1.603, "down": 1.064, "x": 0.0, "y": 0.0, "z": 1.064, "yaw": 0.0}, {"front": 3.092, "back": 1.088, "right": 2.521, "left": 0.797, "up": 1.603, "down": 1.064, "x": 0.0, "y": 0.0, "z": 1.064, "yaw": 0.0}, {"front": 3.092, "back": 1.088, "right": 2.521, "left": 0.797, "up": 1.603, "down": 1.064, "x": 0.0, "y": 0.0, "z": 1.064, "yaw": 0.0}, {"front": 3.092, "back": 1.088, "right": 2.521, "left": 0.797, "up": 1.603, "down": 1.057, "x": 0.0, "y": 0.0, "z": 1.057, "yaw": 0.0}, {"front": 3.092, "back": 1.088, "right": 2.521, "left": 0.797, "up": 1.603, "down": 1.057, "x": 0.0, "y": 0.0, "z": 1.057, "yaw": 0.0}, {"front": 32.766, "back": 1.088, "right": 2.521, "left": 0.797, "up": 1.603, "down": 1.057, "x": 0.0, "y": 0.0, "z": 1.057, "yaw": 0.0}, {"front": 32.766, "back": 1.087, "right": 2.521, "left": 0.797, "up": 1.603, "down": 1.057, "x": 0.0, "y": 0.0, "z": 1.057, "yaw": 0.0}, {"front": 32.766, "back": 1.087, "right": 2.521, "left": 0.815, "up": 1.61, "down": 1.057, "x": 0.0, "y": 0.0, "z": 1.057, "yaw": 0.0}, {"front": 32.766, "back": 1.087, "right": 2.516, "left": 0.815, "up": 1.61, "down": 1.057, "x": 0.0, "y": 0.0, "z": 1.057, "yaw": 0.0}, {"front": 32.766, "back": 1.087, "right": 2.516, "left": 0.815, "up": 1.61, "down": 1.061, "x": 0.0, "y": 0.0, "z": 1.061, "yaw": 0.0}, {"front": 32.766, "back": 1.087, "right": 2.516, "left": 0.815, "up": 1.61, "down": 1.061, "x": 0.0, "y": 0.0, "z": 1.061, "yaw": 0.0}, {"front": 32.766, "back": 1.087, "right": 2.516, "left": 0.815, "up": 1.61, "down": 1.061, "x": 0.0, "y": 0.0, "z": 1.061, "yaw": 0.0}, {"front": 32.766, "back": 1.087, "right": 2.516, "left": 0.815, "up": 1.61, "down": 1.061, "x": 0.0, "y": 0.0, "z": 1.061, "yaw": 0.0}, {"front": 32.766, "back": 1.087, "right": 2.516, "left": 0.815, "up": 1.61, "down": 1.063, "x": 0.0, "y": 0.0, "z": 1.063, "yaw": 0.0}, {"front": 32.766, "back": 1.087, "right": 2.516, "left": 0.815, "up": 1.61, "down": 1.063, "x": 0.0, "y": 0.0, "z": 1.063, "yaw": 0.0}, {"front": 3.067, "back": 1.087, "right": 2.516, "left": 0.815, "up": 1.61, "down": 1.063, "x": 0.0, "y": 0.0, "z": 1.063, "yaw": 0.0}, {"front": 3.067, "back": 1.093, "right": 2.516, "left": 0.815, "up": 1.61, "down": 1.063, "x": 0.0, "y": 0.0, "z": 1.063, "yaw": 0.0}, {"front": 3.067, "back": 1.093, "right": 2.516, "left": 0.837, "up": 1.614, "down": 1.063, "x": 0.0, "y": 0.0, "z": 1.063, "yaw": 0.0}, {"front": 3.067, "back": 1.093, "right": 2.506, "left": 0.837, "up": 1.614, "down": 1.063, "x": 0.0, "y": 0.0, "z": 1.063, "yaw": 0.0}, {"front": 3.067, "back": 1.093, "right": 2.506, "left": 0.837, "up": 1.614, "down": 1.069, "x": 0.0, "y": 0.0, "z": 1.069, "yaw": 0.0}, {"front": 3.067, "back": 1.093, "right": 2.506, "left": 0.837, "up": 1.614, "down": 1.069, "x": 0.0, "y": 0.0, "z": 1.069, "yaw": 0.0}, {"front": 3.067, "back": 1.093, "right": 2.506, "left": 0.837, "up": 1.614, "down": 1.069, "x": 0.0, "y": 0.0, "z": 1.069, "yaw": 0.0}, {"front": 3.067, "back": 1.093, "right": 2.506, "left": 0.837, "up": 1.614, "down": 1.069, "x": 0.0, "y": 0.0, "z": 1.069, "yaw": 0.0}, {"front": 3.067, "back": 1.093, "right": 2.506, "left": 0.837, "up": 1.614, "down": 1.074, "x": 0.0, "y": 0.0, "z": 1.074, "yaw": 0.0}, {"front": 3.067, "back": 1.093, "right": 2.506, "left": 0.837, "up": 1.614, "down": 1.074, "x": 0.0, "y": 0.0, "z": 1.074, "yaw": 0.0}, {"front": 3.079, "back": 1.093, "right": 2.506, "left": 0.837, "up": 1.614, "down": 1.074, "x": 0.0, "y": 0.0, "z": 1.074, "yaw": 0.0}, {"front": 3.079, "back": 1.095, "right": 2.506, "left": 0.837, "up": 1.614, "down": 1.074, "x": 0.0, "y": 0.0, "z": 1.074, "yaw": 0.0}, {"front": 3.079, "back": 1.095, "right": 2.506, "left": 0.86, "up": 1.612, "down": 1.074, "x": 0.0, "y": 0.0, "z": 1.074, "yaw": 0.0}, {"front": 3.079, "back": 1.095, "right": 2.509, "left": 0.86, "up": 1.612, "down": 1.074, "x": 0.0, "y": 0.0, "z": 1.074, "yaw": 0.0}, {"front": 3.079, "back": 1.095, "right": 2.509, "left": 0.86, "up": 1.612, "down": 1.069, "x": 0.0, "y": 0.0, "z": 1.069, "yaw": 0.0}, {"front": 3.079, "back": 1.095, "right": 2.509, "left": 0.86, "up": 1.612, "down": 1.069, "x": 0.0, "y": 0.0, "z": 1.069, "yaw": 0.0}, {"front": 3.079, "back": 1.095, "right": 2.509, "left": 0.86, "up": 1.612, "down": 1.069, "x": 0.0, "y": 0.0, "z": 1.069, "yaw": 0.0}, {"front": 3.079, "back": 1.095, "right": 2.509, "left": 0.86, "up": 1.612, "down": 1.069, "x": 0.0, "y": 0.0, "z": 1.069, "yaw": 0.0}, {"front": 3.079, "back": 1.095, "right": 2.509, "left": 0.86, "up": 1.612, "down": 1.066, "x": 0.0, "y": 0.0, "z": 1.066, "yaw": 0.0}, {"front": 3.079, "back": 1.095, "right": 2.509, "left": 0.86, "up": 1.612, "down": 1.066, "x": 0.0, "y": 0.0, "z": 1.066, "yaw": 0.0}, {"front": 3.055, "back": 1.095, "right": 2.509, "left": 0.86, "up": 1.612, "down": 1.066, "x": 0.0, "y": 0.0, "z": 1.066, "yaw": 0.0}, {"front": 3.055, "back": 1.088, "right": 2.509, "left": 0.86, "up": 1.612, "down": 1.066, "x": 0.0, "y": 0.0, "z": 1.066, "yaw": 0.0}, {"front": 3.055, "back": 1.088, "right": 2.509, "left": 0.892, "up": 1.607, "down": 1.066, "x": 0.0, "y": 0.0, "z": 1.066, "yaw": 0.0}, {"front": 3.055, "back": 1.088, "right": 2.505, "left": 0.892, "up": 1.607, "down": 1.066, "x": 0.0, "y": 0.0, "z": 1.066, "yaw": 0.0}, {"front": 3.055, "back": 1.088, "right": 2.505, "left": 0.892, "up": 1.607, "down": 1.069, "x": 0.0, "y": 0.0, "z": 1.069, "yaw": 0.0}, {"front": 3.055, "back": 1.088, "right": 2.505, "left": 0.892, "up": 1.607, "down": 1.069, "x": 0.0, "y": 0.0, "z": 1.069, "yaw": 0.0}, {"front": 3.055, "back": 1.088, "right": 2.505, "left": 0.892, "up": 1.607, "down": 1.069, "x": 0.0, "y": 0.0, "z": 1.069, "yaw": 0.0}, {"front": 3.055, "back": 1.088, "right": 2.505, "left": 0.892, "up": 1.607, "down": 1.069, "x": 0.0, "y": 0.0, "z": 1.069, "yaw": 0.0}, {"front": 3.055, "back": 1.088, "right": 2.505, "left": 0.892, "up": 1.607, "down": 1.065, "x": 0.0, "y": 0.0, "z": 1.065, "yaw": 0.0}, {"front": 3.055, "back": 1.088, "right": 2.505, "left": 0.892, "up": 1.607, "down": 1.065, "x": 0.0, "y": 0.0, "z": 1.065, "yaw": 0.0}, {"front": 32.766, "back": 1.088, "right": 2.505, "left": 0.892, "up": 1.607, "down": 1.065, "x": 0.0, "y": 0.0, "z": 1.065, "yaw": 0.0}, {"front": 32.766, "back": 1.082, "right": 2.505, "left": 0.892, "up": 1.607, "down": 1.065, "x": 0.0, "y": 0.0, "z": 1.065, "yaw": 0.0}, {"front": 32.766, "back": 1.082, "right": 2.505, "left": 0.818, "up": 1.611, "down": 1.065, "x": 0.0, "y": 0.0, "z": 1.065, "yaw": 0.0}, {"front": 32.766, "back": 1.082, "right": 2.513, "left": 0.818, "up": 1.611, "down": 1.065, "x": 0.0, "y": 0.0, "z": 1.065, "yaw": 0.0}, {"front": 32.766, "back": 1.082, "right": 2.513, "left": 0.818, "up": 1.611, "down": 1.064, "x": 0.0, "y": 0.0, "z": 1.064, "yaw": 0.0}, {"front": 32.766, "back": 1.082, "right": 2.513, "left": 0.818, "up": 1.611, "down": 1.064, "x": 0.0, "y": 0.0, "z": 1.064, "yaw": 0.0}, {"front": 32.766, "back": 1.082, "right": 2.513, "left": 0.818, "up": 1.611, "down": 1.064, "x": 0.0, "y": 0.0, "z": 1.064, "yaw": 0.0}, {"front": 32.766, "back": 1.082, "right": 2.513, "left": 0.818, "up": 1.611, "down": 1.064, "x": 0.0, "y": 0.0, "z": 1.064, "yaw": 0.0}, {"front": 32.766, "back": 1.082, "right": 2.513, "left": 0.818, "up": 1.611, "down": 1.061, "x": 0.0, "y": 0.0, "z": 1.061, "yaw": 0.0}, {"front": 32.766, "back": 1.082, "right": 2.513, "left": 0.818, "up": 1.611, "down": 1.061, "x": 0.0, "y": 0.0, "z": 1.061, "yaw": 0.0}, {"front": 3.09, "back": 1.082, "right": 2.513, "left": 0.818, "up": 1.611, "down": 1.061, "x": 0.0, "y": 0.0, "z": 1.061, "yaw": 0.0}, {"front": 3.09, "back": 1.079, "right": 2.513, "left": 0.818, "up": 1.611, "down": 1.061, "x": 0.0, "y": 0.0, "z": 1.061, "yaw": 0.0}, {"front": 3.09, "back": 1.079, "right": 2.513, "left": 0.784, "up": 1.612, "down": 1.061, "x": 0.0, "y": 0.0, "z": 1.061, "yaw": 0.0}, {"front": 3.09, "back": 1.079, "right": 2.526, "left": 0.784, "up": 1.612, "down": 1.061, "x": 0.0, "y": 0.0, "z": 1.061, "yaw": 0.0}, {"front": 3.09, "back": 1.079, "right": 2.526, "left": 0.784, "up": 1.612, "down": 1.06, "x": 0.0, "y": 0.0, "z": 1.06, "yaw": 0.0}, {"front": 3.09, "back": 1.079, "right": 2.526, "left": 0.784, "up": 1.612, "down": 1.06, "x": 0.0, "y": 0.0, "z": 1.06, "yaw": 0.0}, {"front": 3.09, "back": 1.079, "right": 2.526, "left": 0.784, "up": 1.612, "down": 1.06, "x": 0.0, "y": 0.0, "z": 1.06, "yaw": 0.0}, {"front": 3.09, "back": 1.079, "right": 2.526, "left": 0.784, "up": 1.612, "down": 1.06, "x": 0.0, "y": 0.0, "z": 1.06, "yaw": 0.0}, {"front": 3.09, "back": 1.079, "right": 2.526, "left": 0.784, "up": 1.612, "down": 1.06, "x": 0.0, "y": 0.0, "z": 1.06, "yaw": 0.0}, {"front": 3.09, "back": 1.079, "right": 2.526, "left": 0.784, "up": 1.612, "down": 1.06, "x": 0.0, "y": 0.0, "z": 1.06, "yaw": 0.0}, {"front": 32.766, "back": 1.079, "right": 2.526, "left": 0.784, "up": 1.612, "down": 1.06, "x": 0.0, "y": 0.0, "z": 1.06, "yaw": 0.0}, {"front": 32.766, "back": 1.071, "right": 2.526, "left": 0.784, "up": 1.612, "down": 1.06, "x": 0.0, "y": 0.0, "z": 1.06, "yaw": 0.0}, {"front": 32.766, "back": 1.071, "right": 2.526, "left": 0.773, "up": 1.608, "down": 1.06, "x": 0.0, "y": 0.0, "z": 1.06, "yaw": 0.0}, {"front": 32.766, "back": 1.071, "right": 2.546, "left": 0.773, "up": 1.608, "down": 1.06, "x": 0.0, "y": 0.0, "z": 1.06, "yaw": 0.0}, {"front": 32.766, "back": 1.071, "right": 2.546, "left": 0.773, "up": 1.608, "down": 1.059, "x": 0.0, "y": 0.0, "z": 1.059, "yaw": 0.0}, {"front": 32.766, "back": 1.071, "right": 2.546, "left": 0.773, "up": 1.608, "down": 1.059, "x": 0.0, "y": 0.0, "z": 1.059, "yaw": 0.0}, {"front": 32.766, "back": 1.071, "right": 2.546, "left": 0.773, "up": 1.608, "down": 1.059, "x": 0.0, "y": 0.0, "z": 1.059, "yaw": 0.0}, {"front": 32.766, "back": 1.071, "right": 2.546, "left": 0.773, "up": 1.608, "down": 1.059, "x": 0.0, "y": 0.0, "z": 1.059, "yaw": 0.0}, {"front": 32.766, "back": 1.071, "right": 2.546, "left": 0.773, "up": 1.608, "down": 1.06, "x": 0.0, "y": 0.0, "z": 1.06, "yaw": 0.0}, {"front": 32.766, "back": 1.071, "right": 2.546, "left": 0.773, "up": 1.608, "down": 1.06, "x": 0.0, "y": 0.0, "z": 1.06, "yaw": 0.0}, {"front": 3.11, "back": 1.071, "right": 2.546, "left": 0.773, "up": 1.608, "down": 1.06, "x": 0.0, "y": 0.0, "z": 1.06, "yaw": 0.0}, {"front": 3.11, "back": 1.061, "right": 2.546, "left": 0.773, "up": 1.608, "down": 1.06, "x": 0.0, "y": 0.0, "z": 1.06, "yaw": 0.0}, {"front": 3.11, "back": 1.061, "right": 2.546, "left": 0.788, "up": 1.614, "down": 1.06, "x": 0.0, "y": 0.0, "z": 1.06, "yaw": 0.0}, {"front": 3.11, "back": 1.061, "right": 2.54, "left": 0.788, "up": 1.614, "down": 1.06, "x": 0.0, "y": 0.0, "z": 1.06, "yaw": 0.0}, {"front": 3.11, "back": 1.061, "right": 2.54, "left": 0.788, "up": 1.614, "down": 1.058, "x": 0.0, "y": 0.0, "z": 1.058, "yaw": 0.0}, {"front": 3.11, "back": 1.061, "right": 2.54, "left": 0.788, "up": 1.614, "down": 1.058, "x": 0.0, "y": 0.0, "z": 1.058, "yaw": 0.0}, {"front": 3.11, "back": 1.061, "right": 2.54, "left": 0.788, "up": 1.614, "down": 1.058, "x": 0.0, "y": 0.0, "z": 1.058, "yaw": 0.0}, {"front": 3.11, "back": 1.061, "right": 2.54, "left": 0.788, "up": 1.614, "down": 1.058, "x": 0.0, "y": 0.0, "z": 1.058, "yaw": 0.0}, {"front": 3.11, "back": 1.061, "right": 2.54, "left": 0.788, "up": 1.614, "down": 1.065, "x": 0.0, "y": 0.0, "z": 1.065, "yaw": 0.0}, {"front": 3.11, "back": 1.061, "right": 2.54, "left": 0.788, "up": 1.614, "down": 1.065, "x": 0.0, "y": 0.0, "z": 1.065, "yaw": 0.0}, {"front": 32.766, "back": 1.061, "right": 2.54, "left": 0.788, "up": 1.614, "down": 1.065, "x": 0.0, "y": 0.0, "z": 1.065, "yaw": 0.0}, {"front": 32.766, "back": 1.065, "right": 2.54, "left": 0.788, "up": 1.614, "down": 1.065, "x": 0.0, "y": 0.0, "z": 1.065, "yaw": 0.0}, {"front": 32.766, "back": 1.065, "right": 2.54, "left": 0.781, "up": 1.621, "down": 1.065, "x": 0.0, "y": 0.0, "z": 1.065, "yaw": 0.0}, {"front": 32.766, "back": 1.065, "right": 2.513, "left": 0.781, "up": 1.621, "down": 1.065, "x": 0.0, "y": 0.0, "z": 1.065, "yaw": 0.0}, {"front": 32.766, "back": 1.065, "right": 2.513, "left": 0.781, "up": 1.621, "down": 1.064, "x": 0.0, "y": 0.0, "z": 1.064, "yaw": 0.0}, {"front": 32.766, "back": 1.065, "right": 2.513, "left": 0.781, "up": 1.621, "down": 1.064, "x": 0.0, "y": 0.0, "z": 1.064, "yaw": 0.0}, {"front": 32.766, "back": 1.065, "right": 2.513, "left": 0.781, "up": 1.621, "down": 1.064, "x": 0.0, "y": 0.0, "z": 1.064, "yaw": 0.0}, {"front": 32.766, "back": 1.065, "right": 2.513, "left": 0.781, "up": 1.621, "down": 1.064, "x": 0.0, "y": 0.0, "z": 1.064, "yaw": 0.0}, {"front": 32.766, "back": 1.065, "right": 2.513, "left": 0.781, "up": 1.621, "down": 1.065, "x": 0.0, "y": 0.0, "z": 1.065, "yaw": 0.0}, {"front": 32.766, "back": 1.065, "right": 2.513, "left": 0.781, "up": 1.621, "down": 1.065, "x": 0.0, "y": 0.0, "z": 1.065, "yaw": 0.0}, {"front": 3.128, "back": 1.065, "right": 2.513, "left": 0.781, "up": 1.621, "down": 1.065, "x": 0.0, "y": 0.0, "z": 1.065, "yaw": 0.0}, {"front": 3.128, "back": 1.059, "right": 2.513, "left": 0.781, "up": 1.621, "down": 1.065, "x": 0.0, "y": 0.0, "z": 1.065, "yaw": 0.0}, {"front": 3.128, "back": 1.059, "right": 2.513, "left": 0.765, "up": 1.619, "down": 1.065, "x": 0.0, "y": 0.0, "z": 1.065, "yaw": 0.0}, {"front": 3.128, "back": 1.059, "right": 2.527, "left": 0.765, "up": 1.619, "down": 1.065, "x": 0.0, "y": 0.0, "z": 1.065, "yaw": 0.0}, {"front": 3.128, "back": 1.059, "right": 2.527, "left": 0.765, "up": 1.619, "down": 1.06, "x": 0.0, "y": 0.0, "z": 1.06, "yaw": 0.0}, {"front": 3.128, "back": 1.059, "right": 2.527, "left": 0.765, "up": 1.619, "down": 1.06, "x": 0.0, "y": 0.0, "z": 1.06, "yaw": 0.0}, {"front": 3.128, "back": 1.059, "right": 2.527, "left": 0.765, "up": 1.619, "down": 1.06, "x": 0.0, "y": 0.0, "z": 1.06, "yaw": 0.0}, {"front": 3.128, "back": 1.059, "right": 2.527, "left": 0.765, "up": 1.619, "down": 1.06, "x": 0.0, "y": 0.0, "z": 1.06, "yaw": 0.0}, {"front": 3.128, "back": 1.059, "right": 2.527, "left": 0.765, "up": 1.619, "down": 1.058, "x": 0.0, "y": 0.0, "z": 1.058, "yaw": 0.0}, {"front": 3.128, "back": 1.059, "right": 2.527, "left": 0.765, "up": 1.619, "down": 1.058, "x": 0.0, "y": 0.0, "z": 1.058, "yaw": 0.0}, {"front": 3.095, "back": 1.059, "right": 2.527, "left": 0.765, "up": 1.619, "down": 1.058, "x": 0.0, "y": 0.0, "z": 1.058, "yaw": 0.0}, {"front": 3.095, "back": 1.061, "right": 2.527, "left": 0.765, "up": 1.619, "down": 1.058, "x": 0.0, "y": 0.0, "z": 1.058, "yaw": 0.0}, {"front": 3.095, "back": 1.061, "right": 2.527, "left": 0.752, "up": 1.623, "down": 1.058, "x": 0.0, "y": 0.0, "z": 1.058, "yaw": 0.0}, {"front": 3.095, "back": 1.061, "right": 2.541, "left": 0.752, "up": 1.623, "down": 1.058, "x": 0.0, "y": 0.0, "z": 1.058, "yaw": 0.0}, {"front": 3.095, "back": 1.061, "right": 2.541, "left": 0.752, "up": 1.623, "down": 1.054, "x": 0.0, "y": 0.0, "z": 1.054, "yaw": 0.0}, {"front": 3.095, "back": 1.061, "right": 2.541, "left": 0.752, "up": 1.623, "down": 1.054, "x": 0.0, "y": 0.0, "z": 1.054, "yaw": 0.0}, {"front": 3.095, "back": 1.061, "right": 2.541, "left": 0.752, "up": 1.623, "down": 1.054, "x": 0.0, "y": 0.0, "z": 1.054, "yaw": 0.0}, {"front": 3.095, "back": 1.061, "right": 2.541, "left": 0.752, "up": 1.623, "down": 1.054, "x": 0.0, "y": 0.0, "z": 1.054, "yaw": 0.0}, {"front": 3.095, "back": 1.061, "right": 2.541, "left": 0.752, "up": 1.623, "down": 1.05, "x": 0.0, "y": 0.0, "z": 1.05, "yaw": 0.0}, {"front": 3.095, "back": 1.061, "right": 2.541, "left": 0.752, "up": 1.623, "down": 1.05, "x": 0.0, "y": 0.0, "z": 1.05, "yaw": 0.0}, {"front": 32.766, "back": 1.061, "right": 2.541, "left": 0.752, "up": 1.623, "down": 1.05, "x": 0.0, "y": 0.0, "z": 1.05, "yaw": 0.0}, {"front": 32.766, "back": 1.059, "right": 2.541, "left": 0.752, "up": 1.623, "down": 1.05, "x": 0.0, "y": 0.0, "z": 1.05, "yaw": 0.0}, {"front": 32.766, "back": 1.059, "right": 2.541, "left": 0.802, "up": 1.615, "down": 1.05, "x": 0.0, "y": 0.0, "z": 1.05, "yaw": 0.0}, {"front": 32.766, "back": 1.059, "right": 2.54, "left": 0.802, "up": 1.615, "down": 1.05, "x": 0.0, "y": 0.0, "z": 1.05, "yaw": 0.0}, {"front": 32.766, "back": 1.059, "right": 2.54, "left": 0.802, "up": 1.615, "down": 1.054, "x": 0.0, "y": 0.0, "z": 1.054, "yaw": 0.0}, {"front": 32.766, "back": 1.059, "right": 2.54, "left": 0.802, "up": 1.615, "down": 1.054, "x": 0.0, "y": 0.0, "z": 1.054, "yaw": 0.0}, {"front": 32.766, "back": 1.059, "right": 2.54, "left": 0.802, "up": 1.615, "down": 1.054, "x": 0.0, "y": 0.0, "z": 1.054, "yaw": 0.0}, {"front": 32.766, "back": 1.059, "right": 2.54, "left": 0.802, "up": 1.615, "down": 1.054, "x": 0.0, "y": 0.0, "z": 1.054, "yaw": 0.0}, {"front": 32.766, "back": 1.059, "right": 2.54, "left": 0.802, "up": 1.615, "down": 1.049, "x": 0.0, "y": 0.0, "z": 1.049, "yaw": 0.0}, {"front": 32.766, "back": 1.059, "right": 2.54, "left": 0.802, "up": 1.615, "down": 1.049, "x": 0.0, "y": 0.0, "z": 1.049, "yaw": 0.0}, {"front": 3.091, "back": 1.059, "right": 2.54, "left": 0.802, "up": 1.615, "down": 1.049, "x": 0.0, "y": 0.0, "z": 1.049, "yaw": 0.0}, {"front": 3.091, "back": 1.076, "right": 2.54, "left": 0.802, "up": 1.615, "down": 1.049, "x": 0.0, "y": 0.0, "z": 1.049, "yaw": 0.0}, {"front": 3.091, "back": 1.076, "right": 2.54, "left": 0.78, "up": 1.624, "down": 1.049, "x": 0.0, "y": 0.0, "z": 1.049, "yaw": 0.0}, {"front": 3.091, "back": 1.076, "right": 2.53, "left": 0.78, "up": 1.624, "down": 1.049, "x": 0.0, "y": 0.0, "z": 1.049, "yaw": 0.0}, {"front": 3.091, "back": 1.076, "right": 2.53, "left": 0.78, "up": 1.624, "down": 1.049, "x": 0.0, "y": 0.0, "z": 1.049, "yaw": 0.0}, {"front": 3.091, "back": 1.076, "right": 2.53, "left": 0.78, "up": 1.624, "down": 1.049, "x": 0.0, "y": 0.0, "z": 1.049, "yaw": 0.0}, {"front": 3.091, "back": 1.076, "right": 2.53, "left": 0.78, "up": 1.624, "down": 1.049, "x": 0.0, "y": 0.0, "z": 1.049, "yaw": 0.0}, {"front": 3.091, "back": 1.076, "right": 2.53, "left": 0.78, "up": 1.624, "down": 1.049, "x": 0.0, "y": 0.0, "z": 1.049, "yaw": 0.0}, {"front": 3.091, "back": 1.076, "right": 2.53, "left": 0.78, "up": 1.624, "down": 1.051, "x": 0.0, "y": 0.0, "z": 1.051, "yaw": 0.0}, {"front": 3.091, "back": 1.076, "right": 2.53, "left": 0.78, "up": 1.624, "down": 1.051, "x": 0.0, "y": 0.0, "z": 1.051, "yaw": 0.0}, {"front": 3.087, "back": 1.076, "right": 2.53, "left": 0.78, "up": 1.624, "down": 1.051, "x": 0.0, "y": 0.0, "z": 1.051, "yaw": 0.0}, {"front": 3.087, "back": 1.075, "right": 2.53, "left": 0.78, "up": 1.624, "down": 1.051, "x": 0.0, "y": 0.0, "z": 1.051, "yaw": 0.0}, {"front": 3.087, "back": 1.075, "right": 2.53, "left": 0.78, "up": 1.623, "down": 1.051, "x": 0.0, "y": 0.0, "z": 1.051, "yaw": 0.0}, {"front": 3.087, "back": 1.075, "right": 2.525, "left": 0.78, "up": 1.623, "down": 1.051, "x": 0.0, "y": 0.0, "z": 1.051, "yaw": 0.0}, {"front": 3.087, "back": 1.075, "right": 2.525, "left": 0.78, "up": 1.623, "down": 1.053, "x": 0.0, "y": 0.0, "z": 1.053, "yaw": 0.0}, {"front": 3.087, "back": 1.075, "right": 2.525, "left": 0.78, "up": 1.623, "down": 1.053, "x": 0.0, "y": 0.0, "z": 1.053, "yaw": 0.0}, {"front": 3.087, "back": 1.075, "right": 2.525, "left": 0.78, "up": 1.623, "down": 1.053, "x": 0.0, "y": 0.0, "z": 1.053, "yaw": 0.0}, {"front": 3.087, "back": 1.075, "right": 2.525, "left": 0.78, "up": 1.623, "down": 1.053, "x": 0.0, "y": 0.0, "z": 1.053, "yaw": 0.0}, {"front": 3.087, "back": 1.075, "right": 2.525, "left": 0.78, "up": 1.623, "down": 1.053, "x": 0.0, "y": 0.0, "z": 1.053, "yaw": 0.0}, {"front": 3.087, "back": 1.075, "right": 2.525, "left": 0.78, "up": 1.623, "down": 1.053, "x": 0.0, "y": 0.0, "z": 1.053, "yaw": 0.0}, {"front": 32.766, "back": 1.075, "right": 2.525, "left": 0.78, "up": 1.623, "down": 1.053, "x": 0.0, "y": 0.0, "z": 1.053, "yaw": 0.0}, {"front": 32.766, "back": 1.078, "right": 2.525, "left": 0.78, "up": 1.623, "down": 1.053, "x": 0.0, "y": 0.0, "z": 1.053, "yaw": 0.0}, {"front": 32.766, "back": 1.078, "right": 2.525, "left": 0.782, "up": 1.627, "down": 1.053, "x": 0.0, "y": 0.0, "z": 1.053, "yaw": 0.0}, {"front": 32.766, "back": 1.078, "right": 2.519, "left": 0.782, "up": 1.627, "down": 1.053, "x": 0.0, "y": 0.0, "z": 1.053, "yaw": 0.0}, {"front": 32.766, "back": 1.078, "right": 2.519, "left": 0.782, "up": 1.627, "down": 1.047, "x": 0.0, "y": 0.0, "z": 1.047, "yaw": 0.0}, {"front": 32.766, "back": 1.078, "right": 2.519, "left": 0.782, "up": 1.627, "down": 1.047, "x": 0.0, "y": 0.0, "z": 1.047, "yaw": 0.0}, {"front": 32.766, "back": 1.078, "right": 2.519, "left": 0.782, "up": 1.627, "down": 1.047, "x": 0.0, "y": 0.0, "z": 1.047, "yaw": 0.0}, {"front": 32.766, "back": 1.078, "right": 2.519, "left": 0.782, "up": 1.627, "down": 1.047, "x": 0.0, "y": 0.0, "z": 1.047, "yaw": 0.0}, {"front": 32.766, "back": 1.078, "right": 2.519, "left": 0.782, "up": 1.627, "down": 1.048, "x": 0.0, "y": 0.0, "z": 1.048, "yaw": 0.0}, {"front": 32.766, "back": 1.078, "right": 2.519, "left": 0.782, "up": 1.627, "down": 1.048, "x": 0.0, "y": 0.0, "z": 1.048, "yaw": 0.0}, {"front": 32.766, "back": 1.078, "right": 2.519, "left": 0.782, "up": 1.627, "down": 1.048, "x": 0.0, "y": 0.0, "z": 1.048, "yaw": 0.0}, {"front": 32.766, "back": 1.077, "right": 2.519, "left": 0.782, "up": 1.627, "down": 1.048, "x": 0.0, "y": 0.0, "z": 1.048, "yaw": 0.0}, {"front": 32.766, "back": 1.077, "right": 2.519, "left": 0.782, "up": 1.631, "down": 1.048, "x": 0.0, "y": 0.0, "z": 1.048, "yaw": 0.0}, {"front": 32.766, "back": 1.077, "right": 2.517, "left": 0.782, "up": 1.631, "down": 1.048, "x": 0.0, "y": 0.0, "z": 1.048, "yaw": 0.0}, {"front": 32.766, "back": 1.077, "right": 2.517, "left": 0.782, "up": 1.631, "down": 1.047, "x": 0.0, "y": 0.0, "z": 1.047, "yaw": 0.0}, {"front": 32.766, "back": 1.077, "right": 2.517, "left": 0.782, "up": 1.631, "down": 1.047, "x": 0.0, "y": 0.0, "z": 1.047, "yaw": 0.0}, {"front": 32.766, "back": 1.077, "right": 2.517, "left": 0.782, "up": 1.631, "down": 1.047, "x": 0.0, "y": 0.0, "z": 1.047, "yaw": 0.0}, {"front": 32.766, "back": 1.077, "right": 2.517, "left": 0.782, "up": 1.631, "down": 1.047, "x": 0.0, "y": 0.0, "z": 1.047, "yaw": 0.0}, {"front": 32.766, "back": 1.077, "right": 2.517, "left": 0.782, "up": 1.631, "down": 1.047, "x": 0.0, "y": 0.0, "z": 1.047, "yaw": 0.0}, {"front": 32.766, "back": 1.077, "right": 2.517, "left": 0.782, "up": 1.631, "down": 1.047, "x": 0.0, "y": 0.0, "z": 1.047, "yaw": 0.0}, {"front": 3.08, "back": 1.077, "right": 2.517, "left": 0.782, "up": 1.631, "down": 1.047, "x": 0.0, "y": 0.0, "z": 1.047, "yaw": 0.0}, {"front": 3.08, "back": 1.078, "right": 2.517, "left": 0.782, "up": 1.631, "down": 1.047, "x": 0.0, "y": 0.0, "z": 1.047, "yaw": 0.0}, {"front": 3.08, "back": 1.078, "right": 2.517, "left": 0.774, "up": 1.628, "down": 1.047, "x": 0.0, "y": 0.0, "z": 1.047, "yaw": 0.0}, {"front": 3.08, "back": 1.078, "right": 2.528, "left": 0.774, "up": 1.628, "down": 1.047, "x": 0.0, "y": 0.0, "z": 1.047, "yaw": 0.0}, {"front": 3.08, "back": 1.078, "right": 2.528, "left": 0.774, "up": 1.628, "down": 1.049, "x": 0.0, "y": 0.0, "z": 1.049, "yaw": 0.0}, {"front": 3.08, "back": 1.078, "right": 2.528, "left": 0.774, "up": 1.628, "down": 1.049, "x": 0.0, "y": 0.0, "z": 1.049, "yaw": 0.0}, {"front": 3.08, "back": 1.078, "right": 2.528, "left": 0.774, "up": 1.628, "down": 1.049, "x": 0.0, "y": 0.0, "z": 1.049, "yaw": 0.0}, {"front": 3.08, "back": 1.078, "right": 2.528, "left": 0.774, "up": 1.628, "down": 1.049, "x": 0.0, "y": 0.0, "z": 1.049, "yaw": 0.0}, {"front": 3.08, "back": 1.078, "right": 2.528, "left": 0.774, "up": 1.628, "down": 1.042, "x": 0.0, "y": 0.0, "z": 1.042, "yaw": 0.0}, {"front": 3.08, "back": 1.078, "right": 2.528, "left": 0.774, "up": 1.628, "down": 1.042, "x": 0.0, "y": 0.0, "z": 1.042, "yaw": 0.0}, {"front": 3.084, "back": 1.078, "right": 2.528, "left": 0.774, "up": 1.628, "down": 1.042, "x": 0.0, "y": 0.0, "z": 1.042, "yaw": 0.0}, {"front": 3.084, "back": 1.081, "right": 2.528, "left": 0.774, "up": 1.628, "down": 1.042, "x": 0.0, "y": 0.0, "z": 1.042, "yaw": 0.0}, {"front": 3.084, "back": 1.081, "right": 2.528, "left": 0.771, "up": 1.625, "down": 1.042, "x": 0.0, "y": 0.0, "z": 1.042, "yaw": 0.0}, {"front": 3.084, "back": 1.081, "right": 2.534, "left": 0.771, "up": 1.625, "down": 1.042, "x": 0.0, "y": 0.0, "z": 1.042, "yaw": 0.0}, {"front": 3.084, "back": 1.081, "right": 2.534, "left": 0.771, "up": 1.625, "down": 1.05, "x": 0.0, "y": 0.0, "z": 1.05, "yaw": 0.0}, {"front": 3.084, "back": 1.081, "right": 2.534, "left": 0.771, "up": 1.625, "down": 1.05, "x": 0.0, "y": 0.0, "z": 1.05, "yaw": 0.0}, {"front": 3.084, "back": 1.081, "right": 2.534, "left": 0.771, "up": 1.625, "down": 1.05, "x": 0.0, "y": 0.0, "z": 1.05, "yaw": 0.0}, {"front": 3.084, "back": 1.081, "right": 2.534, "left": 0.771, "up": 1.625, "down": 1.05, "x": 0.0, "y": 0.0, "z": 1.05, "yaw": 0.0}, {"front": 3.084, "back": 1.081, "right": 2.534, "left": 0.771, "up": 1.625, "down": 1.047, "x": 0.0, "y": 0.0, "z": 1.047, "yaw": 0.0}, {"front": 3.084, "back": 1.081, "right": 2.534, "left": 0.771, "up": 1.625, "down": 1.047, "x": 0.0, "y": 0.0, "z": 1.047, "yaw": 0.0}, {"front": 3.081, "back": 1.081, "right": 2.534, "left": 0.771, "up": 1.625, "down": 1.047, "x": 0.0, "y": 0.0, "z": 1.047, "yaw": 0.0}, {"front": 3.081, "back": 1.068, "right": 2.534, "left": 0.771, "up": 1.625, "down": 1.047, "x": 0.0, "y": 0.0, "z": 1.047, "yaw": 0.0}, {"front": 3.081, "back": 1.068, "right": 2.534, "left": 0.759, "up": 1.624, "down": 1.047, "x": 0.0, "y": 0.0, "z": 1.047, "yaw": 0.0}, {"front": 3.081, "back": 1.068, "right": 2.542, "left": 0.759, "up": 1.624, "down": 1.047, "x": 0.0, "y": 0.0, "z": 1.047, "yaw": 0.0}, {"front": 3.081, "back": 1.068, "right": 2.542, "left": 0.759, "up": 1.624, "down": 1.045, "x": 0.0, "y": 0.0, "z": 1.045, "yaw": 0.0}, {"front": 3.081, "back": 1.068, "right": 2.542, "left": 0.759, "up": 1.624, "down": 1.045, "x": 0.0, "y": 0.0, "z": 1.045, "yaw": 0.0}, {"front": 3.081, "back": 1.068, "right": 2.542, "left": 0.759, "up": 1.624, "down": 1.045, "x": 0.0, "y": 0.0, "z": 1.045, "yaw": 0.0}, {"front": 3.081, "back": 1.068, "right": 2.542, "left": 0.759, "up": 1.624, "down": 1.045, "x": 0.0, "y": 0.0, "z": 1.045, "yaw": 0.0}, {"front": 3.081, "back": 1.068, "right": 2.542, "left": 0.759, "up": 1.624, "down": 1.05, "x": 0.0, "y": 0.0, "z": 1.05, "yaw": 0.0}, {"front": 3.081, "back": 1.068, "right": 2.542, "left": 0.759, "up": 1.624, "down": 1.05, "x": 0.0, "y": 0.0, "z": 1.05, "yaw": 0.0}, {"front": 3.088, "back": 1.068, "right": 2.542, "left": 0.759, "up": 1.624, "down": 1.05, "x": 0.0, "y": 0.0, "z": 1.05, "yaw": 0.0}, {"front": 3.088, "back": 1.064, "right": 2.542, "left": 0.759, "up": 1.624, "down": 1.05, "x": 0.0, "y": 0.0, "z": 1.05, "yaw": 0.0}, {"front": 3.088, "back": 1.064, "right": 2.542, "left": 0.752, "up": 1.625, "down": 1.05, "x": 0.0, "y": 0.0, "z": 1.05, "yaw": 0.0}, {"front": 3.088, "back": 1.064, "right": 2.546, "left": 0.752, "up": 1.625, "down": 1.05, "x": 0.0, "y": 0.0, "z": 1.05, "yaw": 0.0}, {"front": 3.088, "back": 1.064, "right": 2.546, "left": 0.752, "up": 1.625, "down": 1.047, "x": 0.0, "y": 0.0, "z": 1.047, "yaw": 0.0}, {"front": 3.088, "back": 1.064, "right": 2.546, "left": 0.752, "up": 1.625, "down": 1.047, "x": 0.0, "y": 0.0, "z": 1.047, "yaw": 0.0}, {"front": 3.088, "back": 1.064, "right": 2.546, "left": 0.752, "up": 1.625, "down": 1.047, "x": 0.0, "y": 0.0, "z": 1.047, "yaw": 0.0}, {"front": 3.088, "back": 1.064, "right": 2.546, "left": 0.752, "up": 1.625, "down": 1.047, "x": 0.0, "y": 0.0, "z": 1.047, "yaw": 0.0}, {"front": 3.088, "back": 1.064, "right": 2.546, "left": 0.752, "up": 1.625, "down": 1.051, "x": 0.0, "y": 0.0, "z": 1.051, "yaw": 0.0}, {"front": 3.088, "back": 1.064, "right": 2.546, "left": 0.752, "up": 1.625, "down": 1.051, "x": 0.0, "y": 0.0, "z": 1.051, "yaw": 0.0}, {"front": 3.107, "back": 1.064, "right": 2.546, "left": 0.752, "up": 1.625, "down": 1.051, "x": 0.0, "y": 0.0, "z": 1.051, "yaw": 0.0}, {"front": 3.107, "back": 1.062, "right": 2.546, "left": 0.752, "up": 1.625, "down": 1.051, "x": 0.0, "y": 0.0, "z": 1.051, "yaw": 0.0}, {"front": 3.107, "back": 1.062, "right": 2.546, "left": 0.75, "up": 1.629, "down": 1.051, "x": 0.0, "y": 0.0, "z": 1.051, "yaw": 0.0}, {"front": 3.107, "back": 1.062, "right": 2.538, "left": 0.75, "up": 1.629, "down": 1.051, "x": 0.0, "y": 0.0, "z": 1.051, "yaw": 0.0}, {"front": 3.107, "back": 1.062, "right": 2.538, "left": 0.75, "up": 1.629, "down": 1.049, "x": 0.0, "y": 0.0, "z": 1.049, "yaw": 0.0}, {"front": 3.107, "back": 1.062, "right": 2.538, "left": 0.75, "up": 1.629, "down": 1.049, "x": 0.0, "y": 0.0, "z": 1.049, "yaw": 0.0}, {"front": 3.107, "back": 1.062, "right": 2.538, "left": 0.75, "up": 1.629, "down": 1.049, "x": 0.0, "y": 0.0, "z": 1.049, "yaw": 0.0}, {"front": 3.107, "back": 1.062, "right": 2.538, "left": 0.75, "up": 1.629, "down": 1.049, "x": 0.0, "y": 0.0, "z": 1.049, "yaw": 0.0}, {"front": 3.107, "back": 1.062, "right": 2.538, "left": 0.75, "up": 1.629, "down": 1.043, "x": 0.0, "y": 0.0, "z": 1.043, "yaw": 0.0}, {"front": 3.107, "back": 1.062, "right": 2.538, "left": 0.75, "up": 1.629, "down": 1.043, "x": 0.0, "y": 0.0, "z": 1.043, "yaw": 0.0}, {"front": 32.766, "back": 1.062, "right": 2.538, "left": 0.75, "up": 1.629, "down": 1.043, "x": 0.0, "y": 0.0, "z": 1.043, "yaw": 0.0}, {"front": 32.766, "back": 1.064, "right": 2.538, "left": 0.75, "up": 1.629, "down": 1.043, "x": 0.0, "y": 0.0, "z": 1.043, "yaw": 0.0}, {"front": 32.766, "back": 1.064, "right": 2.538, "left": 0.746, "up": 1.629, "down": 1.043, "x": 0.0, "y": 0.0, "z": 1.043, "yaw": 0.0}, {"front": 32.766, "back": 1.064, "right": 2.544, "left": 0.746, "up": 1.629, "down": 1.043, "x": 0.0, "y": 0.0, "z": 1.043, "yaw": 0.0}, {"front": 32.766, "back": 1.064, "right": 2.544, "left": 0.746, "up": 1.629, "down": 1.047, "x": 0.0, "y": 0.0, "z": 1.047, "yaw": 0.0}, {"front": 32.766, "back": 1.064, "right": 2.544, "left": 0.746, "up": 1.629, "down": 1.047, "x": 0.0, "y": 0.0, "z": 1.047, "yaw": 0.0}, {"front": 32.766, "back": 1.064, "right": 2.544, "left": 0.746, "up": 1.629, "down": 1.047, "x": 0.0, "y": 0.0, "z": 1.047, "yaw": 0.0}, {"front": 32.766, "back": 1.064, "right": 2.544, "left": 0.746, "up": 1.629, "down": 1.047, "x": 0.0, "y": 0.0, "z": 1.047, "yaw": 0.0}, {"front": 32.766, "back": 1.064, "right": 2.544, "left": 0.746, "up": 1.629, "down": 1.043, "x": 0.0, "y": 0.0, "z": 1.043, "yaw": 0.0}, {"front": 32.766, "back": 1.064, "right": 2.544, "left": 0.746, "up": 1.629, "down": 1.043, "x": 0.0, "y": 0.0, "z": 1.043, "yaw": 0.0}, {"front": 32.766, "back": 1.064, "right": 2.544, "left": 0.746, "up": 1.629, "down": 1.043, "x": 0.0, "y": 0.0, "z": 1.043, "yaw": 0.0}, {"front": 32.766, "back": 1.062, "right": 2.544, "left": 0.746, "up": 1.629, "down": 1.043, "x": 0.0, "y": 0.0, "z": 1.043, "yaw": 0.0}, {"front": 32.766, "back": 1.062, "right": 2.544, "left": 0.747, "up": 1.634, "down": 1.043, "x": 0.0, "y": 0.0, "z": 1.043, "yaw": 0.0}, {"front": 32.766, "back": 1.062, "right": 2.544, "left": 0.747, "up": 1.634, "down": 1.043, "x": 0.0, "y": 0.0, "z": 1.043, "yaw": 0.0}, {"front": 32.766, "back": 1.062, "right": 2.544, "left": 0.747, "up": 1.634, "down": 1.043, "x": 0.0, "y": 0.0, "z": 1.043, "yaw": 0.0}, {"front": 32.766, "back": 1.062, "right": 2.544, "left": 0.747, "up": 1.634, "down": 1.043, "x": 0.0, "y": 0.0, "z": 1.043, "yaw": 0.0}, {"front": 32.766, "back": 1.062, "right": 2.544, "left": 0.747, "up": 1.634, "down": 1.043, "x": 0.0, "y": 0.0, "z": 1.043, "yaw": 0.0}, {"front": 32.766, "back": 1.062, "right": 2.544, "left": 0.747, "up": 1.634, "down": 1.043, "x": 0.0, "y": 0.0, "z": 1.043, "yaw": 0.0}, {"front": 32.766, "back": 1.062, "right": 2.544, "left": 0.747, "up": 1.634, "down": 1.037, "x": 0.0, "y": 0.0, "z": 1.037, "yaw": 0.0}, {"front": 32.766, "back": 1.062, "right": 2.544, "left": 0.747, "up": 1.634, "down": 1.037, "x": 0.0, "y": 0.0, "z": 1.037, "yaw": 0.0}, {"front": 3.077, "back": 1.062, "right": 2.544, "left": 0.747, "up": 1.634, "down": 1.037, "x": 0.0, "y": 0.0, "z": 1.037, "yaw": 0.0}, {"front": 3.077, "back": 1.06, "right": 2.544, "left": 0.747, "up": 1.634, "down": 1.037, "x": 0.0, "y": 0.0, "z": 1.037, "yaw": 0.0}, {"front": 3.077, "back": 1.06, "right": 2.544, "left": 0.741, "up": 1.631, "down": 1.037, "x": 0.0, "y": 0.0, "z": 1.037, "yaw": 0.0}, {"front": 3.077, "back": 1.06, "right": 2.524, "left": 0.741, "up": 1.631, "down": 1.037, "x": 0.0, "y": 0.0, "z": 1.037, "yaw": 0.0}, {"front": 3.077, "back": 1.06, "right": 2.524, "left": 0.741, "up": 1.631, "down": 1.038, "x": 0.0, "y": 0.0, "z": 1.038, "yaw": 0.0}, {"front": 3.077, "back": 1.06, "right": 2.524, "left": 0.741, "up": 1.631, "down": 1.038, "x": 0.0, "y": 0.0, "z": 1.038, "yaw": 0.0}, {"front": 3.077, "back": 1.06, "right": 2.524, "left": 0.741, "up": 1.631, "down": 1.038, "x": 0.0, "y": 0.0, "z": 1.038, "yaw": 0.0}, {"front": 3.077, "back": 1.06, "right": 2.524, "left": 0.741, "up": 1.631, "down": 1.038, "x": 0.0, "y": 0.0, "z": 1.038, "yaw": 0.0}, {"front": 3.077, "back": 1.06, "right": 2.524, "left": 0.741, "up": 1.631, "down": 1.035, "x": 0.0, "y": 0.0, "z": 1.035, "yaw": 0.0}, {"front": 3.077, "back": 1.06, "right": 2.524, "left": 0.741, "up": 1.631, "down": 1.035, "x": 0.0, "y": 0.0, "z": 1.035, "yaw": 0.0}, {"front": 3.099, "back": 1.06, "right": 2.524, "left": 0.741, "up": 1.631, "down": 1.035, "x": 0.0, "y": 0.0, "z": 1.035, "yaw": 0.0}, {"front": 3.099, "back": 1.068, "right": 2.524, "left": 0.741, "up": 1.631, "down": 1.035, "x": 0.0, "y": 0.0, "z": 1.035, "yaw": 0.0}, {"front": 3.099, "back": 1.068, "right": 2.524, "left": 0.74, "up": 1.636, "down": 1.035, "x": 0.0, "y": 0.0, "z": 1.035, "yaw": 0.0}, {"front": 3.099, "back": 1.068, "right": 2.528, "left": 0.74, "up": 1.636, "down": 1.035, "x": 0.0, "y": 0.0, "z": 1.035, "yaw": 0.0}, {"front": 3.099, "back": 1.068, "right": 2.528, "left": 0.74, "up": 1.636, "down": 1.035, "x": 0.0, "y": 0.0, "z": 1.035, "yaw": 0.0}, {"front": 3.099, "back": 1.068, "right": 2.528, "left": 0.74, "up": 1.636, "down": 1.035, "x": 0.0, "y": 0.0, "z": 1.035, "yaw": 0.0}, {"front": 3.099, "back": 1.068, "right": 2.528, "left": 0.74, "up": 1.636, "down": 1.035, "x": 0.0, "y": 0.0, "z": 1.035, "yaw": 0.0}, {"front": 3.099, "back": 1.068, "right": 2.528, "left": 0.74, "up": 1.636, "down": 1.035, "x": 0.0, "y": 0.0, "z": 1.035, "yaw": 0.0}, {"front": 3.099, "back": 1.068, "right": 2.528, "left": 0.74, "up": 1.636, "down": 1.034, "x": 0.0, "y": 0.0, "z": 1.034, "yaw": 0.0}, {"front": 3.099, "back": 1.068, "right": 2.528, "left": 0.74, "up": 1.636, "down": 1.034, "x": 0.0, "y": 0.0, "z": 1.034, "yaw": 0.0}, {"front": 32.766, "back": 1.068, "right": 2.528, "left": 0.74, "up": 1.636, "down": 1.034, "x": 0.0, "y": 0.0, "z": 1.034, "yaw": 0.0}, {"front": 32.766, "back": 1.068, "right": 2.528, "left": 0.74, "up": 1.636, "down": 1.034, "x": 0.0, "y": 0.0, "z": 1.034, "yaw": 0.0}, {"front": 32.766, "back": 1.068, "right": 2.528, "left": 0.743, "up": 1.64, "down": 1.034, "x": 0.0, "y": 0.0, "z": 1.034, "yaw": 0.0}, {"front": 32.766, "back": 1.068, "right": 2.538, "left": 0.743, "up": 1.64, "down": 1.034, "x": 0.0, "y": 0.0, "z": 1.034, "yaw": 0.0}, {"front": 32.766, "back": 1.068, "right": 2.538, "left": 0.743, "up": 1.64, "down": 1.037, "x": 0.0, "y": 0.0, "z": 1.037, "yaw": 0.0}, {"front": 32.766, "back": 1.068, "right": 2.538, "left": 0.743, "up": 1.64, "down": 1.037, "x": 0.0, "y": 0.0, "z": 1.037, "yaw": 0.0}, {"front": 32.766, "back": 1.068, "right": 2.538, "left": 0.743, "up": 1.64, "down": 1.037, "x": 0.0, "y": 0.0, "z": 1.037, "yaw": 0.0}, {"front": 32.766, "back": 1.068, "right": 2.538, "left": 0.743, "up": 1.64, "down": 1.037, "x": 0.0, "y": 0.0, "z": 1.037, "yaw": 0.0}, {"front": 32.766, "back": 1.068, "right": 2.538, "left": 0.743, "up": 1.64, "down": 1.033, "x": 0.0, "y": 0.0, "z": 1.033, "yaw": 0.0}, {"front": 32.766, "back": 1.068, "right": 2.538, "left": 0.743, "up": 1.64, "down": 1.033, "x": 0.0, "y": 0.0, "z": 1.033, "yaw": 0.0}, {"front": 32.766, "back": 1.068, "right": 2.538, "left": 0.743, "up": 1.64, "down": 1.033, "x": 0.0, "y": 0.0, "z": 1.033, "yaw": 0.0}, {"front": 32.766, "back": 1.066, "right": 2.538, "left": 0.743, "up": 1.64, "down": 1.033, "x": 0.0, "y": 0.0, "z": 1.033, "yaw": 0.0}, {"front": 32.766, "back": 1.066, "right": 2.538, "left": 0.739, "up": 1.642, "down": 1.033, "x": 0.0, "y": 0.0, "z": 1.033, "yaw": 0.0}, {"front": 32.766, "back": 1.066, "right": 2.535, "left": 0.739, "up": 1.642, "down": 1.033, "x": 0.0, "y": 0.0, "z": 1.033, "yaw": 0.0}, {"front": 32.766, "back": 1.066, "right": 2.535, "left": 0.739, "up": 1.642, "down": 1.033, "x": 0.0, "y": 0.0, "z": 1.033, "yaw": 0.0}, {"front": 32.766, "back": 1.066, "right": 2.535, "left": 0.739, "up": 1.642, "down": 1.033, "x": 0.0, "y": 0.0, "z": 1.033, "yaw": 0.0}, {"front": 32.766, "back": 1.066, "right": 2.535, "left": 0.739, "up": 1.642, "down": 1.033, "x": 0.0, "y": 0.0, "z": 1.033, "yaw": 0.0}, {"front": 32.766, "back": 1.066, "right": 2.535, "left": 0.739, "up": 1.642, "down": 1.033, "x": 0.0, "y": 0.0, "z": 1.033, "yaw": 0.0}, {"front": 32.766, "back": 1.066, "right": 2.535, "left": 0.739, "up": 1.642, "down": 1.042, "x": 0.0, "y": 0.0, "z": 1.042, "yaw": 0.0}, {"front": 32.766, "back": 1.066, "right": 2.535, "left": 0.739, "up": 1.642, "down": 1.042, "x": 0.0, "y": 0.0, "z": 1.042, "yaw": 0.0}, {"front": 32.766, "back": 1.066, "right": 2.535, "left": 0.739, "up": 1.642, "down": 1.042, "x": 0.0, "y": 0.0, "z": 1.042, "yaw": 0.0}, {"front": 32.766, "back": 1.064, "right": 2.535, "left": 0.739, "up": 1.642, "down": 1.042, "x": 0.0, "y": 0.0, "z": 1.042, "yaw": 0.0}, {"front": 32.766, "back": 1.064, "right": 2.535, "left": 0.731, "up": 1.643, "down": 1.042, "x": 0.0, "y": 0.0, "z": 1.042, "yaw": 0.0}, {"front": 32.766, "back": 1.064, "right": 2.54, "left": 0.731, "up": 1.643, "down": 1.042, "x": 0.0, "y": 0.0, "z": 1.042, "yaw": 0.0}, {"front": 32.766, "back": 1.064, "right": 2.54, "left": 0.731, "up": 1.643, "down": 1.035, "x": 0.0, "y": 0.0, "z": 1.035, "yaw": 0.0}, {"front": 32.766, "back": 1.064, "right": 2.54, "left": 0.731, "up": 1.643, "down": 1.035, "x": 0.0, "y": 0.0, "z": 1.035, "yaw": 0.0}, {"front": 32.766, "back": 1.064, "right": 2.54, "left": 0.731, "up": 1.643, "down": 1.035, "x": 0.0, "y": 0.0, "z": 1.035, "yaw": 0.0}, {"front": 32.766, "back": 1.064, "right": 2.54, "left": 0.731, "up": 1.643, "down": 1.035, "x": 0.0, "y": 0.0, "z": 1.035, "yaw": 0.0}, {"front": 32.766, "back": 1.064, "right": 2.54, "left": 0.731, "up": 1.643, "down": 1.03, "x": 0.0, "y": 0.0, "z": 1.03, "yaw": 0.0}, {"front": 32.766, "back": 1.064, "right": 2.54, "left": 0.731, "up": 1.643, "down": 1.03, "x": 0.0, "y": 0.0, "z": 1.03, "yaw": 0.0}, {"front": 3.105, "back": 1.064, "right": 2.54, "left": 0.731, "up": 1.643, "down": 1.03, "x": 0.0, "y": 0.0, "z": 1.03, "yaw": 0.0}, {"front": 3.105, "back": 1.053, "right": 2.54, "left": 0.731, "up": 1.643, "down": 1.03, "x": 0.0, "y": 0.0, "z": 1.03, "yaw": 0.0}, {"front": 3.105, "back": 1.053, "right": 2.54, "left": 0.718, "up": 1.637, "down": 1.03, "x": 0.0, "y": 0.0, "z": 1.03, "yaw": 0.0}, {"front": 3.105, "back": 1.053, "right": 2.55, "left": 0.718, "up": 1.637, "down": 1.03, "x": 0.0, "y": 0.0, "z": 1.03, "yaw": 0.0}, {"front": 3.105, "back": 1.053, "right": 2.55, "left": 0.718, "up": 1.637, "down": 1.036, "x": 0.0, "y": 0.0, "z": 1.036, "yaw": 0.0}, {"front": 3.105, "back": 1.053, "right": 2.55, "left": 0.718, "up": 1.637, "down": 1.036, "x": 0.0, "y": 0.0, "z": 1.036, "yaw": 0.0}, {"front": 3.105, "back": 1.053, "right": 2.55, "left": 0.718, "up": 1.637, "down": 1.036, "x": 0.0, "y": 0.0, "z": 1.036, "yaw": 0.0}, {"front": 3.105, "back": 1.053, "right": 2.55, "left": 0.718, "up": 1.637, "down": 1.036, "x": 0.0, "y": 0.0, "z": 1.036, "yaw": 0.0}, {"front": 3.105, "back": 1.053, "right": 2.55, "left": 0.718, "up": 1.637, "down": 1.036, "x": 0.0, "y": 0.0, "z": 1.036, "yaw": 0.0}, {"front": 3.105, "back": 1.053, "right": 2.55, "left": 0.718, "up": 1.637, "down": 1.036, "x": 0.0, "y": 0.0, "z": 1.036, "yaw": 0.0}, {"front": 3.105, "back": 1.053, "right": 2.55, "left": 0.718, "up": 1.637, "down": 1.036, "x": 0.0, "y": 0.0, "z": 1.036, "yaw": 0.0}, {"front": 3.105, "back": 1.057, "right": 2.55, "left": 0.718, "up": 1.637, "down": 1.036, "x": 0.0, "y": 0.0, "z": 1.036, "yaw": 0.0}, {"front": 3.105, "back": 1.057, "right": 2.55, "left": 0.7, "up": 1.632, "down": 1.036, "x": 0.0, "y": 0.0, "z": 1.036, "yaw": 0.0}, {"front": 3.105, "back": 1.057, "right": 2.565, "left": 0.7, "up": 1.632, "down": 1.036, "x": 0.0, "y": 0.0, "z": 1.036, "yaw": 0.0}, {"front": 3.105, "back": 1.057, "right": 2.565, "left": 0.7, "up": 1.632, "down": 1.033, "x": 0.0, "y": 0.0, "z": 1.033, "yaw": 0.0}, {"front": 3.105, "back": 1.057, "right": 2.565, "left": 0.7, "up": 1.632, "down": 1.033, "x": 0.0, "y": 0.0, "z": 1.033, "yaw": 0.0}, {"front": 3.105, "back": 1.057, "right": 2.565, "left": 0.7, "up": 1.632, "down": 1.033, "x": 0.0, "y": 0.0, "z": 1.033, "yaw": 0.0}, {"front": 3.105, "back": 1.057, "right": 2.565, "left": 0.7, "up": 1.632, "down": 1.033, "x": 0.0, "y": 0.0, "z": 1.033, "yaw": 0.0}, {"front": 3.105, "back": 1.057, "right": 2.565, "left": 0.7, "up": 1.632, "down": 1.035, "x": 0.0, "y": 0.0, "z": 1.035, "yaw": 0.0}, {"front": 3.105, "back": 1.057, "right": 2.565, "left": 0.7, "up": 1.632, "down": 1.035, "x": 0.0, "y": 0.0, "z": 1.035, "yaw": 0.0}, {"front": 32.766, "back": 1.057, "right": 2.565, "left": 0.7, "up": 1.632, "down": 1.035, "x": 0.0, "y": 0.0, "z": 1.035, "yaw": 0.0}, {"front": 32.766, "back": 1.059, "right": 2.565, "left": 0.7, "up": 1.632, "down": 1.035, "x": 0.0, "y": 0.0, "z": 1.035, "yaw": 0.0}, {"front": 32.766, "back": 1.059, "right": 2.565, "left": 0.694, "up": 1.636, "down": 1.035, "x": 0.0, "y": 0.0, "z": 1.035, "yaw": 0.0}, {"front": 32.766, "back": 1.059, "right": 2.568, "left": 0.694, "up": 1.636, "down": 1.035, "x": 0.0, "y": 0.0, "z": 1.035, "yaw": 0.0}, {"front": 32.766, "back": 1.059, "right": 2.568, "left": 0.694, "up": 1.636, "down": 1.031, "x": 0.0, "y": 0.0, "z": 1.031, "yaw": 0.0}, {"front": 32.766, "back": 1.059, "right": 2.568, "left": 0.694, "up": 1.636, "down": 1.031, "x": 0.0, "y": 0.0, "z": 1.031, "yaw": 0.0}, {"front": 32.766, "back": 1.059, "right": 2.568, "left": 0.694, "up": 1.636, "down": 1.031, "x": 0.0, "y": 0.0, "z": 1.031, "yaw": 0.0}, {"front": 32.766, "back": 1.059, "right": 2.568, "left": 0.694, "up": 1.636, "down": 1.031, "x": 0.0, "y": 0.0, "z": 1.031, "yaw": 0.0}, {"front": 32.766, "back": 1.059, "right": 2.568, "left": 0.694, "up": 1.636, "down": 1.037, "x": 0.0, "y": 0.0, "z": 1.037, "yaw": 0.0}, {"front": 32.766, "back": 1.059, "right": 2.568, "left": 0.694, "up": 1.636, "down": 1.037, "x": 0.0, "y": 0.0, "z": 1.037, "yaw": 0.0}, {"front": 3.124, "back": 1.059, "right": 2.568, "left": 0.694, "up": 1.636, "down": 1.037, "x": 0.0, "y": 0.0, "z": 1.037, "yaw": 0.0}, {"front": 3.124, "back": 1.058, "right": 2.568, "left": 0.694, "up": 1.636, "down": 1.037, "x": 0.0, "y": 0.0, "z": 1.037, "yaw": 0.0}, {"front": 3.124, "back": 1.058, "right": 2.568, "left": 0.688, "up": 1.638, "down": 1.037, "x": 0.0, "y": 0.0, "z": 1.037, "yaw": 0.0}, {"front": 3.124, "back": 1.058, "right": 2.557, "left": 0.688, "up": 1.638, "down": 1.037, "x": 0.0, "y": 0.0, "z": 1.037, "yaw": 0.0}, {"front": 3.124, "back": 1.058, "right": 2.557, "left": 0.688, "up": 1.638, "down": 1.041, "x": 0.0, "y": 0.0, "z": 1.041, "yaw": 0.0}, {"front": 3.124, "back": 1.058, "right": 2.557, "left": 0.688, "up": 1.638, "down": 1.041, "x": 0.0, "y": 0.0, "z": 1.041, "yaw": 0.0}, {"front": 3.124, "back": 1.058, "right": 2.557, "left": 0.688, "up": 1.638, "down": 1.041, "x": 0.0, "y": 0.0, "z": 1.041, "yaw": 0.0}, {"front": 3.124, "back": 1.058, "right": 2.557, "left": 0.688, "up": 1.638, "down": 1.041, "x": 0.0, "y": 0.0, "z": 1.041, "yaw": 0.0}, {"front": 3.124, "back": 1.058, "right": 2.557, "left": 0.688, "up": 1.638, "down": 1.034, "x": 0.0, "y": 0.0, "z": 1.034, "yaw": 0.0}, {"front": 3.124, "back": 1.058, "right": 2.557, "left": 0.688, "up": 1.638, "down": 1.034, "x": 0.0, "y": 0.0, "z": 1.034, "yaw": 0.0}, {"front": 3.099, "back": 1.058, "right": 2.557, "left": 0.688, "up": 1.638, "down": 1.034, "x": 0.0, "y": 0.0, "z": 1.034, "yaw": 0.0}, {"front": 3.099, "back": 1.056, "right": 2.557, "left": 0.688, "up": 1.638, "down": 1.034, "x": 0.0, "y": 0.0, "z": 1.034, "yaw": 0.0}, {"front": 3.099, "back": 1.056, "right": 2.557, "left": 0.689, "up": 1.639, "down": 1.034, "x": 0.0, "y": 0.0, "z": 1.034, "yaw": 0.0}, {"front": 3.099, "back": 1.056, "right": 2.544, "left": 0.689, "up": 1.639, "down": 1.034, "x": 0.0, "y": 0.0, "z": 1.034, "yaw": 0.0}, {"front": 3.099, "back": 1.056, "right": 2.544, "left": 0.689, "up": 1.639, "down": 1.033, "x": 0.0, "y": 0.0, "z": 1.033, "yaw": 0.0}, {"front": 3.099, "back": 1.056, "right": 2.544, "left": 0.689, "up": 1.639, "down": 1.033, "x": 0.0, "y": 0.0, "z": 1.033, "yaw": 0.0}, {"front": 3.099, "back": 1.056, "right": 2.544, "left": 0.689, "up": 1.639, "down": 1.033, "x": 0.0, "y": 0.0, "z": 1.033, "yaw": 0.0}, {"front": 3.099, "back": 1.056, "right": 2.544, "left": 0.689, "up": 1.639, "down": 1.033, "x": 0.0, "y": 0.0, "z": 1.033, "yaw": 0.0}, {"front": 3.099, "back": 1.056, "right": 2.544, "left": 0.689, "up": 1.639, "down": 1.033, "x": 0.0, "y": 0.0, "z": 1.033, "yaw": 0.0}, {"front": 3.099, "back": 1.056, "right": 2.544, "left": 0.689, "up": 1.639, "down": 1.033, "x": 0.0, "y": 0.0, "z": 1.033, "yaw": 0.0}, {"front": 3.104, "back": 1.056, "right": 2.544, "left": 0.689, "up": 1.639, "down": 1.033, "x": 0.0, "y": 0.0, "z": 1.033, "yaw": 0.0}, {"front": 3.104, "back": 1.057, "right": 2.544, "left": 0.689, "up": 1.639, "down": 1.033, "x": 0.0, "y": 0.0, "z": 1.033, "yaw": 0.0}, {"front": 3.104, "back": 1.057, "right": 2.544, "left": 0.684, "up": 1.641, "down": 1.033, "x": 0.0, "y": 0.0, "z": 1.033, "yaw": 0.0}, {"front": 3.104, "back": 1.057, "right": 2.555, "left": 0.684, "up": 1.641, "down": 1.033, "x": 0.0, "y": 0.0, "z": 1.033, "yaw": 0.0}, {"front": 3.104, "back": 1.057, "right": 2.555, "left": 0.684, "up": 1.641, "down": 1.035, "x": 0.0, "y": 0.0, "z": 1.035, "yaw": 0.0}, {"front": 3.104, "back": 1.057, "right": 2.555, "left": 0.684, "up": 1.641, "down": 1.035, "x": 0.0, "y": 0.0, "z": 1.035, "yaw": 0.0}, {"front": 3.104, "back": 1.057, "right": 2.555, "left": 0.684, "up": 1.641, "down": 1.035, "x": 0.0, "y": 0.0, "z": 1.035, "yaw": 0.0}, {"front": 3.104, "back": 1.057, "right": 2.555, "left": 0.684, "up": 1.641, "down": 1.035, "x": 0.0, "y": 0.0, "z": 1.035, "yaw": 0.0}, {"front": 3.104, "back": 1.057, "right": 2.555, "left": 0.684, "up": 1.641, "down": 1.026, "x": 0.0, "y": 0.0, "z": 1.026, "yaw": 0.0}, {"front": 3.104, "back": 1.057, "right": 2.555, "left": 0.684, "up": 1.641, "down": 1.026, "x": 0.0, "y": 0.0, "z": 1.026, "yaw": 0.0}, {"front": 3.093, "back": 1.057, "right": 2.555, "left": 0.684, "up": 1.641, "down": 1.026, "x": 0.0, "y": 0.0, "z": 1.026, "yaw": 0.0}, {"front": 3.093, "back": 1.057, "right": 2.555, "left": 0.684, "up": 1.641, "down": 1.026, "x": 0.0, "y": 0.0, "z": 1.026, "yaw": 0.0}, {"front": 3.093, "back": 1.057, "right": 2.555, "left": 0.693, "up": 1.644, "down": 1.026, "x": 0.0, "y": 0.0, "z": 1.026, "yaw": 0.0}, {"front": 3.093, "back": 1.057, "right": 2.574, "left": 0.693, "up": 1.644, "down": 1.026, "x": 0.0, "y": 0.0, "z": 1.026, "yaw": 0.0}, {"front": 3.093, "back": 1.057, "right": 2.574, "left": 0.693, "up": 1.644, "down": 1.032, "x": 0.0, "y": 0.0, "z": 1.032, "yaw": 0.0}, {"front": 3.093, "back": 1.057, "right": 2.574, "left": 0.693, "up": 1.644, "down": 1.032, "x": 0.0, "y": 0.0, "z": 1.032, "yaw": 0.0}, {"front": 3.093, "back": 1.057, "right": 2.574, "left": 0.693, "up": 1.644, "down": 1.032, "x": 0.0, "y": 0.0, "z": 1.032, "yaw": 0.0}, {"front": 3.093, "back": 1.057, "right": 2.574, "left": 0.693, "up": 1.644, "down": 1.032, "x": 0.0, "y": 0.0, "z": 1.032, "yaw": 0.0}, {"front": 3.093, "back": 1.057, "right": 2.574, "left": 0.693, "up": 1.644, "down": 1.025, "x": 0.0, "y": 0.0, "z": 1.025, "yaw": 0.0}, {"front": 3.093, "back": 1.057, "right": 2.574, "left": 0.693, "up": 1.644, "down": 1.025, "x": 0.0, "y": 0.0, "z": 1.025, "yaw": 0.0}, {"front": 3.082, "back": 1.057, "right": 2.574, "left": 0.693, "up": 1.644, "down": 1.025, "x": 0.0, "y": 0.0, "z": 1.025, "yaw": 0.0}, {"front": 3.082, "back": 1.06, "right": 2.574, "left": 0.693, "up": 1.644, "down": 1.025, "x": 0.0, "y": 0.0, "z": 1.025, "yaw": 0.0}, {"front": 3.082, "back": 1.06, "right": 2.574, "left": 0.694, "up": 1.642, "down": 1.025, "x": 0.0, "y": 0.0, "z": 1.025, "yaw": 0.0}, {"front": 3.082, "back": 1.06, "right": 2.566, "left": 0.694, "up": 1.642, "down": 1.025, "x": 0.0, "y": 0.0, "z": 1.025, "yaw": 0.0}, {"front": 3.082, "back": 1.06, "right": 2.566, "left": 0.694, "up": 1.642, "down": 1.026, "x": 0.0, "y": 0.0, "z": 1.026, "yaw": 0.0}, {"front": 3.082, "back": 1.06, "right": 2.566, "left": 0.694, "up": 1.642, "down": 1.026, "x": 0.0, "y": 0.0, "z": 1.026, "yaw": 0.0}, {"front": 3.082, "back": 1.06, "right": 2.566, "left": 0.694, "up": 1.642, "down": 1.026, "x": 0.0, "y": 0.0, "z": 1.026, "yaw": 0.0}, {"front": 3.082, "back": 1.06, "right": 2.566, "left": 0.694, "up": 1.642, "down": 1.026, "x": 0.0, "y": 0.0, "z": 1.026, "yaw": 0.0}, {"front": 3.082, "back": 1.06, "right": 2.566, "left": 0.694, "up": 1.642, "down": 1.028, "x": 0.0, "y": 0.0, "z": 1.028, "yaw": 0.0}, {"front": 3.082, "back": 1.06, "right": 2.566, "left": 0.694, "up": 1.642, "down": 1.028, "x": 0.0, "y": 0.0, "z": 1.028, "yaw": 0.0}, {"front": 3.107, "back": 1.06, "right": 2.566, "left": 0.694, "up": 1.642, "down": 1.028, "x": 0.0, "y": 0.0, "z": 1.028, "yaw": 0.0}, {"front": 3.107, "back": 1.057, "right": 2.566, "left": 0.694, "up": 1.642, "down": 1.028, "x": 0.0, "y": 0.0, "z": 1.028, "yaw": 0.0}, {"front": 3.107, "back": 1.057, "right": 2.566, "left": 0.703, "up": 1.645, "down": 1.028, "x": 0.0, "y": 0.0, "z": 1.028, "yaw": 0.0}, {"front": 3.107, "back": 1.057, "right": 2.568, "left": 0.703, "up": 1.645, "down": 1.028, "x": 0.0, "y": 0.0, "z": 1.028, "yaw": 0.0}, {"front": 3.107, "back": 1.057, "right": 2.568, "left": 0.703, "up": 1.645, "down": 1.03, "x": 0.0, "y": 0.0, "z": 1.03, "yaw": 0.0}, {"front": 3.107, "back": 1.057, "right": 2.568, "left": 0.703, "up": 1.645, "down": 1.03, "x": 0.0, "y": 0.0, "z": 1.03, "yaw": 0.0}, {"front": 3.107, "back": 1.057, "right": 2.568, "left": 0.703, "up": 1.645, "down": 1.03, "x": 0.0, "y": 0.0, "z": 1.03, "yaw": 0.0}, {"front": 3.107, "back": 1.057, "right": 2.568, "left": 0.703, "up": 1.645, "down": 1.03, "x": 0.0, "y": 0.0, "z": 1.03, "yaw": 0.0}, {"front": 3.107, "back": 1.057, "right": 2.568, "left": 0.703, "up": 1.645, "down": 1.027, "x": 0.0, "y": 0.0, "z": 1.027, "yaw": 0.0}, {"front": 3.107, "back": 1.057, "right": 2.568, "left": 0.703, "up": 1.645, "down": 1.027, "x": 0.0, "y": 0.0, "z": 1.027, "yaw": 0.0}, {"front": 32.766, "back": 1.057, "right": 2.568, "left": 0.703, "up": 1.645, "down": 1.027, "x": 0.0, "y": 0.0, "z": 1.027, "yaw": 0.0}, {"front": 32.766, "back": 1.056, "right": 2.568, "left": 0.703, "up": 1.645, "down": 1.027, "x": 0.0, "y": 0.0, "z": 1.027, "yaw": 0.0}, {"front": 32.766, "back": 1.056, "right": 2.568, "left": 0.713, "up": 1.658, "down": 1.027, "x": 0.0, "y": 0.0, "z": 1.027, "yaw": 0.0}, {"front": 32.766, "back": 1.056, "right": 2.555, "left": 0.713, "up": 1.658, "down": 1.027, "x": 0.0, "y": 0.0, "z": 1.027, "yaw": 0.0}, {"front": 32.766, "back": 1.056, "right": 2.555, "left": 0.713, "up": 1.658, "down": 1.032, "x": 0.0, "y": 0.0, "z": 1.032, "yaw": 0.0}, {"front": 32.766, "back": 1.056, "right": 2.555, "left": 0.713, "up": 1.658, "down": 1.032, "x": 0.0, "y": 0.0, "z": 1.032, "yaw": 0.0}, {"front": 32.766, "back": 1.056, "right": 2.555, "left": 0.713, "up": 1.658, "down": 1.032, "x": 0.0, "y": 0.0, "z": 1.032, "yaw": 0.0}, {"front": 32.766, "back": 1.056, "right": 2.555, "left": 0.713, "up": 1.658, "down": 1.032, "x": 0.0, "y": 0.0, "z": 1.032, "yaw": 0.0}, {"front": 32.766, "back": 1.056, "right": 2.555, "left": 0.713, "up": 1.658, "down": 1.029, "x": 0.0, "y": 0.0, "z": 1.029, "yaw": 0.0}, {"front": 32.766, "back": 1.056, "right": 2.555, "left": 0.713, "up": 1.658, "down": 1.029, "x": 0.0, "y": 0.0, "z": 1.029, "yaw": 0.0}, {"front": 3.078, "back": 1.056, "right": 2.555, "left": 0.713, "up": 1.658, "down": 1.029, "x": 0.0, "y": 0.0, "z": 1.029, "yaw": 0.0}, {"front": 3.078, "back": 1.059, "right": 2.555, "left": 0.713, "up": 1.658, "down": 1.029, "x": 0.0, "y": 0.0, "z": 1.029, "yaw": 0.0}, {"front": 3.078, "back": 1.059, "right": 2.555, "left": 0.719, "up": 1.651, "down": 1.029, "x": 0.0, "y": 0.0, "z": 1.029, "yaw": 0.0}, {"front": 3.078, "back": 1.059, "right": 2.569, "left": 0.719, "up": 1.651, "down": 1.029, "x": 0.0, "y": 0.0, "z": 1.029, "yaw": 0.0}, {"front": 3.078, "back": 1.059, "right": 2.569, "left": 0.719, "up": 1.651, "down": 1.027, "x": 0.0, "y": 0.0, "z": 1.027, "yaw": 0.0}, {"front": 3.078, "back": 1.059, "right": 2.569, "left": 0.719, "up": 1.651, "down": 1.027, "x": 0.0, "y": 0.0, "z": 1.027, "yaw": 0.0}, {"front": 3.078, "back": 1.059, "right": 2.569, "left": 0.719, "up": 1.651, "down": 1.027, "x": 0.0, "y": 0.0, "z": 1.027, "yaw": 0.0}, {"front": 3.078, "back": 1.059, "right": 2.569, "left": 0.719, "up": 1.651, "down": 1.027, "x": 0.0, "y": 0.0, "z": 1.027, "yaw": 0.0}, {"front": 3.078, "back": 1.059, "right": 2.569, "left": 0.719, "up": 1.651, "down": 1.026, "x": 0.0, "y": 0.0, "z": 1.026, "yaw": 0.0}, {"front": 3.078, "back": 1.059, "right": 2.569, "left": 0.719, "up": 1.651, "down": 1.026, "x": 0.0, "y": 0.0, "z": 1.026, "yaw": 0.0}, {"front": 3.098, "back": 1.059, "right": 2.569, "left": 0.719, "up": 1.651, "down": 1.026, "x": 0.0, "y": 0.0, "z": 1.026, "yaw": 0.0}]